{
    "sourceFile": "游戏分析/环境叙事设计理念.md",
    "activeCommit": 0,
    "commits": [
        {
            "activePatchIndex": 63,
            "patches": [
                {
                    "date": 1766136630438,
                    "content": "Index: \n===================================================================\n--- \n+++ \n"
                },
                {
                    "date": 1766136639277,
                    "content": "Index: \n===================================================================\n--- \n+++ \n@@ -19,9 +19,9 @@\n ## 环境叙事：公式 + 落地\r\n \r\n ### 氛围公式（胡金铨）\r\n \r\n-#### 环境的氛围 = 光 + 烟雾 + 景 + 运镜 + 人 + 音\r\n+#### 美的氛围 = 光 + 烟雾 + 景 + 运镜 + 人 + 音\r\n \r\n - **光**：明暗 / 色温 / 聚焦 / 位置 / 光斑 / 光晕 / 光影 → 定调 + 引导 + 规则提示\r\n   - **安全/存档/恢复（示例）**：暖光/稳定光源/聚光范围 = “安全锚点”（篝火、灯笼、神龛、阵法、营地）\r\n   - **危险/禁入（示例）**：偏红/闪烁/逆光剪影/强对比 = “风险提示”（敌巢、陷阱区、Boss场）\r\n"
                },
                {
                    "date": 1766136651596,
                    "content": "Index: \n===================================================================\n--- \n+++ \n@@ -15,9 +15,9 @@\n > 判断标准：**不看 UI、不读字，玩家能否靠环境完成“导航 + 理解 + 感受”。**\r\n \r\n ---\r\n \r\n-## 环境叙事：公式 + 落地\r\n+## 环境叙事：公式\r\n \r\n ### 氛围公式（胡金铨）\r\n \r\n #### 美的氛围 = 光 + 烟雾 + 景 + 运镜 + 人 + 音\r\n"
                },
                {
                    "date": 1766136662260,
                    "content": "Index: \n===================================================================\n--- \n+++ \n@@ -15,9 +15,9 @@\n > 判断标准：**不看 UI、不读字，玩家能否靠环境完成“导航 + 理解 + 感受”。**\r\n \r\n ---\r\n \r\n-## 环境叙事：公式\r\n+## 环境叙事-公式\r\n \r\n ### 氛围公式（胡金铨）\r\n \r\n #### 美的氛围 = 光 + 烟雾 + 景 + 运镜 + 人 + 音\r\n@@ -47,9 +47,9 @@\n ![环境表现设计理念分析](环境/Attached_image2.png)\r\n ![环境表现设计理念分析](环境/Attached_image3.png)\r\n ![环境表现设计理念分析](环境/Attached_image4.png)\r\n \r\n-## 场景制作：最小交付（MVP）清单\r\n+##  环境叙事-公式\r\n \r\n > 每做一个新场景，至少交付下面 5 条；做不到就先别加“精细材质”。\r\n \r\n - **静态基底**：形体清晰、可读（不追求精细）。\r\n"
                },
                {
                    "date": 1766136676293,
                    "content": "Index: \n===================================================================\n--- \n+++ \n@@ -47,9 +47,9 @@\n ![环境表现设计理念分析](环境/Attached_image2.png)\r\n ![环境表现设计理念分析](环境/Attached_image3.png)\r\n ![环境表现设计理念分析](环境/Attached_image4.png)\r\n \r\n-##  环境叙事-公式\r\n+## 环境叙事-公式\r\n \r\n > 每做一个新场景，至少交付下面 5 条；做不到就先别加“精细材质”。\r\n \r\n - **静态基底**：形体清晰、可读（不追求精细）。\r\n@@ -65,9 +65,9 @@\n - 音效很多，但**没有提示/反馈/引导**作用。\r\n \r\n ---\r\n \r\n-## 资源分配建议（避免做偏）\r\n+### 资源分配建议（避免做偏）\r\n \r\n > 你当前的判断：**“动态效果/音/光/后处理”往往比“模型细节”更能提升氛围与可读性**。\r\n \r\n - **核心玩法系统**：60–70%\r\n"
                },
                {
                    "date": 1766136703914,
                    "content": "Index: \n===================================================================\n--- \n+++ \n@@ -76,9 +76,9 @@\n - **写实堆料**：0%（除非团队能完整撑住写实链路）\r\n \r\n ---\r\n \r\n-## 模块化模板（可复用，不写论文）\r\n+## 环境叙事-交互\r\n \r\n > **使用方式**：把下面内容当“交互词典”。只列**可读信号 + 规则/交互效果 + 反馈**，不写实现细节（字段/触发/技术方案）。\r\n \r\n ### A. 水：注重水的物理，而不是水的表现，保证玩家能读懂水的状态，水物理是拓展玩法基础\r\n"
                },
                {
                    "date": 1766136712978,
                    "content": "Index: \n===================================================================\n--- \n+++ \n@@ -76,9 +76,9 @@\n - **写实堆料**：0%（除非团队能完整撑住写实链路）\r\n \r\n ---\r\n \r\n-## 环境叙事-交互\r\n+## 环境叙事-交互反馈\r\n \r\n > **使用方式**：把下面内容当“交互词典”。只列**可读信号 + 规则/交互效果 + 反馈**，不写实现细节（字段/触发/技术方案）。\r\n \r\n ### A. 水：注重水的物理，而不是水的表现，保证玩家能读懂水的状态，水物理是拓展玩法基础\r\n"
                },
                {
                    "date": 1766136778555,
                    "content": "Index: \n===================================================================\n--- \n+++ \n@@ -47,9 +47,9 @@\n ![环境表现设计理念分析](环境/Attached_image2.png)\r\n ![环境表现设计理念分析](环境/Attached_image3.png)\r\n ![环境表现设计理念分析](环境/Attached_image4.png)\r\n \r\n-## 环境叙事-公式\r\n+## 环境叙事-落地\r\n \r\n > 每做一个新场景，至少交付下面 5 条；做不到就先别加“精细材质”。\r\n \r\n - **静态基底**：形体清晰、可读（不追求精细）。\r\n"
                },
                {
                    "date": 1766136804412,
                    "content": "Index: \n===================================================================\n--- \n+++ \n@@ -57,14 +57,8 @@\n - **音效一层**：底噪（风/虫/水/城镇）+ 一条机制反馈（脚步/草/水/火）。\r\n - **光照一层**：主光 + 明暗对比（至少能引导一处重点）。\r\n - **后处理一层**：统一色调（冷/暖/压暗/对比度）让风格收敛。\r\n \r\n-### 反面指标（出现就砍）\r\n-\r\n-- 堆材质细节，但**玩家看不出路径/交互点/危险**。\r\n-- 堆粒子/后处理，但**玩法没有任何变化或反馈**。\r\n-- 音效很多，但**没有提示/反馈/引导**作用。\r\n-\r\n ---\r\n \r\n ### 资源分配建议（避免做偏）\r\n \r\n"
                },
                {
                    "date": 1766136811074,
                    "content": "Index: \n===================================================================\n--- \n+++ \n@@ -59,19 +59,8 @@\n - **后处理一层**：统一色调（冷/暖/压暗/对比度）让风格收敛。\r\n \r\n ---\r\n \r\n-### 资源分配建议（避免做偏）\r\n-\r\n-> 你当前的判断：**“动态效果/音/光/后处理”往往比“模型细节”更能提升氛围与可读性**。\r\n-\r\n-- **核心玩法系统**：60–70%\r\n-- **风格统一（环境表现系统化）**：20–30%\r\n-- **基础视觉效果（够用即可）**：5–10%\r\n-- **写实堆料**：0%（除非团队能完整撑住写实链路）\r\n-\r\n----\r\n-\r\n ## 环境叙事-交互反馈\r\n \r\n > **使用方式**：把下面内容当“交互词典”。只列**可读信号 + 规则/交互效果 + 反馈**，不写实现细节（字段/触发/技术方案）。\r\n \r\n"
                },
                {
                    "date": 1766136823837,
                    "content": "Index: \n===================================================================\n--- \n+++ \n@@ -61,10 +61,8 @@\n ---\r\n \r\n ## 环境叙事-交互反馈\r\n \r\n-> **使用方式**：把下面内容当“交互词典”。只列**可读信号 + 规则/交互效果 + 反馈**，不写实现细节（字段/触发/技术方案）。\r\n-\r\n ### A. 水：注重水的物理，而不是水的表现，保证玩家能读懂水的状态，水物理是拓展玩法基础\r\n \r\n \r\n **核心思维**：水的价值来自“玩法机制”，视觉只要“能读懂”。\r\n"
                },
                {
                    "date": 1766136837003,
                    "content": "Index: \n===================================================================\n--- \n+++ \n@@ -61,9 +61,9 @@\n ---\r\n \r\n ## 环境叙事-交互反馈\r\n \r\n-### A. 水：注重水的物理，而不是水的表现，保证玩家能读懂水的状态，水物理是拓展玩法基础\r\n+### 1. **水**：注重水的物理，而不是水的表现，保证玩家能读懂水的状态，水物理是拓展玩法基础\r\n \r\n \r\n **核心思维**：水的价值来自“玩法机制”，视觉只要“能读懂”。\r\n \r\n"
                },
                {
                    "date": 1766136846106,
                    "content": "Index: \n===================================================================\n--- \n+++ \n@@ -61,9 +61,9 @@\n ---\r\n \r\n ## 环境叙事-交互反馈\r\n \r\n-### 1. **水**：注重水的物理，而不是水的表现，保证玩家能读懂水的状态，水物理是拓展玩法基础\r\n+### 1. <color=red>水</color>：注重水的物理，而不是水的表现，保证玩家能读懂水的状态，水物理是拓展玩法基础\r\n \r\n \r\n **核心思维**：水的价值来自“玩法机制”，视觉只要“能读懂”。\r\n \r\n"
                },
                {
                    "date": 1766136860235,
                    "content": "Index: \n===================================================================\n--- \n+++ \n@@ -61,9 +61,9 @@\n ---\r\n \r\n ## 环境叙事-交互反馈\r\n \r\n-### 1. <color=red>水</color>：注重水的物理，而不是水的表现，保证玩家能读懂水的状态，水物理是拓展玩法基础\r\n+### 1. 水：注重水的物理，而不是水的表现，保证玩家能读懂水的状态，水物理是拓展玩法基础\r\n \r\n \r\n **核心思维**：水的价值来自“玩法机制”，视觉只要“能读懂”。\r\n \r\n"
                },
                {
                    "date": 1766136883332,
                    "content": "Index: \n===================================================================\n--- \n+++ \n@@ -61,9 +61,9 @@\n ---\r\n \r\n ## 环境叙事-交互反馈\r\n \r\n-### 1. 水：注重水的物理，而不是水的表现，保证玩家能读懂水的状态，水物理是拓展玩法基础\r\n+### 1. <color=red>水：注重水的物理，而不是水的表现，保证玩家能读懂水的状态，水物理是拓展玩法基础</color>\r\n \r\n \r\n **核心思维**：水的价值来自“玩法机制”，视觉只要“能读懂”。\r\n \r\n"
                },
                {
                    "date": 1766136900044,
                    "content": "Index: \n===================================================================\n--- \n+++ \n@@ -61,9 +61,9 @@\n ---\r\n \r\n ## 环境叙事-交互反馈\r\n \r\n-### 1. <color=red>水：注重水的物理，而不是水的表现，保证玩家能读懂水的状态，水物理是拓展玩法基础</color>\r\n+### 1. <font color=\"red\">水：注重水的物理，而不是水的表现，保证玩家能读懂水的状态，水物理是拓展玩法基础</font>\r\n \r\n \r\n **核心思维**：水的价值来自“玩法机制”，视觉只要“能读懂”。\r\n \r\n"
                },
                {
                    "date": 1766136910273,
                    "content": "Index: \n===================================================================\n--- \n+++ \n@@ -61,9 +61,9 @@\n ---\r\n \r\n ## 环境叙事-交互反馈\r\n \r\n-### 1. <font color=\"red\">水：注重水的物理，而不是水的表现，保证玩家能读懂水的状态，水物理是拓展玩法基础</font>\r\n+### 1. <font color=\"red\",size=5>水</font>：注重水的物理，而不是水的表现，保证玩家能读懂水的状态，水物理是拓展玩法基础\r\n \r\n \r\n **核心思维**：水的价值来自“玩法机制”，视觉只要“能读懂”。\r\n \r\n"
                },
                {
                    "date": 1766136927121,
                    "content": "Index: \n===================================================================\n--- \n+++ \n@@ -61,9 +61,9 @@\n ---\r\n \r\n ## 环境叙事-交互反馈\r\n \r\n-### 1. <font color=\"red\",size=5>水</font>：注重水的物理，而不是水的表现，保证玩家能读懂水的状态，水物理是拓展玩法基础\r\n+### 1. <font color=\"red\",b>水</font>：注重水的物理，而不是水的表现，保证玩家能读懂水的状态，水物理是拓展玩法基础\r\n \r\n \r\n **核心思维**：水的价值来自“玩法机制”，视觉只要“能读懂”。\r\n \r\n"
                },
                {
                    "date": 1766136936214,
                    "content": "Index: \n===================================================================\n--- \n+++ \n@@ -61,9 +61,9 @@\n ---\r\n \r\n ## 环境叙事-交互反馈\r\n \r\n-### 1. <font color=\"red\",b>水</font>：注重水的物理，而不是水的表现，保证玩家能读懂水的状态，水物理是拓展玩法基础\r\n+### 1. <font color=\"red\">**水**</font>：注重水的物理，而不是水的表现，保证玩家能读懂水的状态，水物理是拓展玩法基础\r\n \r\n \r\n **核心思维**：水的价值来自“玩法机制”，视觉只要“能读懂”。\r\n \r\n"
                },
                {
                    "date": 1766136993317,
                    "content": "Index: \n===================================================================\n--- \n+++ \n@@ -61,9 +61,9 @@\n ---\r\n \r\n ## 环境叙事-交互反馈\r\n \r\n-### 1. <font color=\"red\">**水**</font>：注重水的物理，而不是水的表现，保证玩家能读懂水的状态，水物理是拓展玩法基础\r\n+### 1. 注重<font color=\"red\">水</font>的物理，而不是水的表现，保证玩家能读懂水的状态，水物理是拓展玩法基础\r\n \r\n \r\n **核心思维**：水的价值来自“玩法机制”，视觉只要“能读懂”。\r\n \r\n"
                },
                {
                    "date": 1766137027483,
                    "content": "Index: \n===================================================================\n--- \n+++ \n@@ -61,11 +61,13 @@\n ---\r\n \r\n ## 环境叙事-交互反馈\r\n \r\n-### 1. 注重<font color=\"red\">水</font>的物理，而不是水的表现，保证玩家能读懂水的状态，水物理是拓展玩法基础\r\n+### 1. <font color=\"red\"> \"水\"  </font>\r\n \r\n+注重水的物理，而不是水的表现，保证玩家能读懂水的状态，水物理是拓展玩法基础\r\n \r\n+\r\n **核心思维**：水的价值来自“玩法机制”，视觉只要“能读懂”。\r\n \r\n - **区域**：浅水/深水/危险/安全（颜色/纹理即可区分）\r\n - **状态**：平静/波浪/结冰/污染/魔法（用动效或贴图变化表达）\r\n"
                },
                {
                    "date": 1766137036595,
                    "content": "Index: \n===================================================================\n--- \n+++ \n@@ -63,9 +63,9 @@\n ## 环境叙事-交互反馈\r\n \r\n ### 1. <font color=\"red\"> \"水\"  </font>\r\n \r\n-注重水的物理，而不是水的表现，保证玩家能读懂水的状态，水物理是拓展玩法基础\r\n+**注重水的物理，而不是水的表现，保证玩家能读懂水的状态，水物理是拓展玩法基础**\r\n \r\n \r\n **核心思维**：水的价值来自“玩法机制”，视觉只要“能读懂”。\r\n \r\n"
                },
                {
                    "date": 1766137071746,
                    "content": "Index: \n===================================================================\n--- \n+++ \n@@ -61,9 +61,9 @@\n ---\r\n \r\n ## 环境叙事-交互反馈\r\n \r\n-### 1. <font color=\"red\"> \"水\"  </font>\r\n+### 1. <font color=\"#4a7372\"> \"水\"  </font>\r\n \r\n **注重水的物理，而不是水的表现，保证玩家能读懂水的状态，水物理是拓展玩法基础**\r\n \r\n \r\n"
                },
                {
                    "date": 1766137083600,
                    "content": "Index: \n===================================================================\n--- \n+++ \n@@ -84,9 +84,9 @@\n   - 探索：隐藏/资源/机关\r\n \r\n ![环境表现设计理念分析](环境/水.png)\r\n \r\n-### B. 环境音效：底噪 + 事件 + 反馈（够用即可）\r\n+### 2. <font color=\"red\"> \"环境音效\"  </font>\r\n \r\n **核心思维**：音效要支持玩法（提示/反馈/引导），其次才是“好听”。\r\n \r\n - **底噪（氛围）**：风/虫/水/城镇人声（让场景“活”）\r\n"
                },
                {
                    "date": 1766137101386,
                    "content": "Index: \n===================================================================\n--- \n+++ \n@@ -84,9 +84,9 @@\n   - 探索：隐藏/资源/机关\r\n \r\n ![环境表现设计理念分析](环境/水.png)\r\n \r\n-### 2. <font color=\"red\"> \"环境音效\"  </font>\r\n+### 2. <font color=\"red\"> \"音\"  </font>\r\n \r\n **核心思维**：音效要支持玩法（提示/反馈/引导），其次才是“好听”。\r\n \r\n - **底噪（氛围）**：风/虫/水/城镇人声（让场景“活”）\r\n"
                },
                {
                    "date": 1766137107005,
                    "content": "Index: \n===================================================================\n--- \n+++ \n@@ -84,9 +84,9 @@\n   - 探索：隐藏/资源/机关\r\n \r\n ![环境表现设计理念分析](环境/水.png)\r\n \r\n-### 2. <font color=\"red\"> \"音\"  </font>\r\n+### 2. <font color=\"#5c4eb1\"> \"音\"  </font>\r\n \r\n **核心思维**：音效要支持玩法（提示/反馈/引导），其次才是“好听”。\r\n \r\n - **底噪（氛围）**：风/虫/水/城镇人声（让场景“活”）\r\n"
                },
                {
                    "date": 1766137126608,
                    "content": "Index: \n===================================================================\n--- \n+++ \n@@ -86,9 +86,9 @@\n ![环境表现设计理念分析](环境/水.png)\r\n \r\n ### 2. <font color=\"#5c4eb1\"> \"音\"  </font>\r\n \r\n-**核心思维**：音效要支持玩法（提示/反馈/引导），其次才是“好听”。\r\n+**核心思维**：音效要支持玩法（提示/反馈/引导）及氛围营造，其次才是“好听”。\r\n \r\n - **底噪（氛围）**：风/虫/水/城镇人声（让场景“活”）\r\n - **事件提示（引导）**：远处怪、机关、目标区域（方向性/距离衰减）\r\n - **交互反馈（规则，尽量全面）**：\r\n"
                },
                {
                    "date": 1766137148389,
                    "content": "Index: \n===================================================================\n--- \n+++ \n@@ -100,9 +100,9 @@\n   - **危险提示**：远处吼叫/脚步逼近/低频轰鸣（提前预警与引导）\r\n   - **状态提示**：湿/冻/燃/毒/流血/诅咒（用“音色差异”让玩家听出状态）\r\n   - **地形危险**：塌陷/碎石滚落/冰裂/泥陷（用预警音提示“将要发生”）\r\n \r\n-### C. 光源：三作用 + 分类（保留你的分类体系）\r\n+### C. <font color=\"#f57f17\"> \"光\"  </font>\r\n \r\n **核心思维**：光源的三个作用——**玩法机制、氛围营造、地图引导**。\r\n \r\n #### 光源的地图引导（最重要）\r\n"
                },
                {
                    "date": 1766137160907,
                    "content": "Index: \n===================================================================\n--- \n+++ \n@@ -100,9 +100,9 @@\n   - **危险提示**：远处吼叫/脚步逼近/低频轰鸣（提前预警与引导）\r\n   - **状态提示**：湿/冻/燃/毒/流血/诅咒（用“音色差异”让玩家听出状态）\r\n   - **地形危险**：塌陷/碎石滚落/冰裂/泥陷（用预警音提示“将要发生”）\r\n \r\n-### C. <font color=\"#f57f17\"> \"光\"  </font>\r\n+###  <font color=\"#f57f17\"> \"光\"  </font>\r\n \r\n **核心思维**：光源的三个作用——**玩法机制、氛围营造、地图引导**。\r\n \r\n #### 光源的地图引导（最重要）\r\n"
                },
                {
                    "date": 1766137167767,
                    "content": "Index: \n===================================================================\n--- \n+++ \n@@ -61,9 +61,9 @@\n ---\r\n \r\n ## 环境叙事-交互反馈\r\n \r\n-### 1. <font color=\"#4a7372\"> \"水\"  </font>\r\n+###  <font color=\"#4a7372\"> \"水\"  </font>\r\n \r\n **注重水的物理，而不是水的表现，保证玩家能读懂水的状态，水物理是拓展玩法基础**\r\n \r\n \r\n@@ -84,9 +84,9 @@\n   - 探索：隐藏/资源/机关\r\n \r\n ![环境表现设计理念分析](环境/水.png)\r\n \r\n-### 2. <font color=\"#5c4eb1\"> \"音\"  </font>\r\n+###  <font color=\"#5c4eb1\"> \"音\"  </font>\r\n \r\n **核心思维**：音效要支持玩法（提示/反馈/引导）及氛围营造，其次才是“好听”。\r\n \r\n - **底噪（氛围）**：风/虫/水/城镇人声（让场景“活”）\r\n"
                },
                {
                    "date": 1766137176006,
                    "content": "Index: \n===================================================================\n--- \n+++ \n@@ -99,9 +99,9 @@\n   - **交互与UI替代**：开门/拾取/机关启动/宝箱（确认反馈）\r\n   - **危险提示**：远处吼叫/脚步逼近/低频轰鸣（提前预警与引导）\r\n   - **状态提示**：湿/冻/燃/毒/流血/诅咒（用“音色差异”让玩家听出状态）\r\n   - **地形危险**：塌陷/碎石滚落/冰裂/泥陷（用预警音提示“将要发生”）\r\n-\r\n+---\r\n ###  <font color=\"#f57f17\"> \"光\"  </font>\r\n \r\n **核心思维**：光源的三个作用——**玩法机制、氛围营造、地图引导**。\r\n \r\n"
                },
                {
                    "date": 1766137183822,
                    "content": "Index: \n===================================================================\n--- \n+++ \n@@ -83,8 +83,9 @@\n   - 战斗：水 + 雷/冰/火（范围/状态/遮挡）\r\n   - 探索：隐藏/资源/机关\r\n \r\n ![环境表现设计理念分析](环境/水.png)\r\n+---\r\n \r\n ###  <font color=\"#5c4eb1\"> \"音\"  </font>\r\n \r\n **核心思维**：音效要支持玩法（提示/反馈/引导）及氛围营造，其次才是“好听”。\r\n@@ -100,8 +101,9 @@\n   - **危险提示**：远处吼叫/脚步逼近/低频轰鸣（提前预警与引导）\r\n   - **状态提示**：湿/冻/燃/毒/流血/诅咒（用“音色差异”让玩家听出状态）\r\n   - **地形危险**：塌陷/碎石滚落/冰裂/泥陷（用预警音提示“将要发生”）\r\n ---\r\n+\r\n ###  <font color=\"#f57f17\"> \"光\"  </font>\r\n \r\n **核心思维**：光源的三个作用——**玩法机制、氛围营造、地图引导**。\r\n \r\n"
                },
                {
                    "date": 1766137189155,
                    "content": "Index: \n===================================================================\n--- \n+++ \n@@ -83,8 +83,9 @@\n   - 战斗：水 + 雷/冰/火（范围/状态/遮挡）\r\n   - 探索：隐藏/资源/机关\r\n \r\n ![环境表现设计理念分析](环境/水.png)\r\n+\r\n ---\r\n \r\n ###  <font color=\"#5c4eb1\"> \"音\"  </font>\r\n \r\n"
                },
                {
                    "date": 1766137209386,
                    "content": "Index: \n===================================================================\n--- \n+++ \n@@ -0,0 +1,141 @@\n+# 环境表现设计理念分析（可一眼扫懂版）\r\n+\r\n+## 一句话结论\r\n+\r\n+**环境表现不是“堆美术”，而是用一套可复用的元素（光 / 动效 / 烟雾粒子 / 音 / 场景结构）去完成：引导、反馈、氛围，并尽量与玩法规则绑定。**\r\n+\r\n+---\r\n+\r\n+## 核心原理（最重要的 3 件事）\r\n+\r\n+- **引导**：玩家不用 UI 也知道“往哪走、哪里重要、哪里危险”。（明暗对比 / 色温 / 方向性音效 / 动态吸引点）\r\n+- **反馈**：玩家的行为会被环境回应，让世界“活”。（脚步/草动/水波/火光变化/粒子散射）\r\n+- **氛围**：玩家能感受到“这里是什么地方、此刻是什么情绪”。（冷暖、留白、空气感、音景层次）\r\n+\r\n+> 判断标准：**不看 UI、不读字，玩家能否靠环境完成“导航 + 理解 + 感受”。**\r\n+\r\n+---\r\n+\r\n+## 环境叙事-公式\r\n+\r\n+### 氛围公式（胡金铨）\r\n+\r\n+#### 美的氛围 = 光 + 烟雾 + 景 + 运镜 + 人 + 音\r\n+\r\n+- **光**：明暗 / 色温 / 聚焦 / 位置 / 光斑 / 光晕 / 光影 → 定调 + 引导 + 规则提示\r\n+  - **安全/存档/恢复（示例）**：暖光/稳定光源/聚光范围 = “安全锚点”（篝火、灯笼、神龛、阵法、营地）\r\n+  - **危险/禁入（示例）**：偏红/闪烁/逆光剪影/强对比 = “风险提示”（敌巢、陷阱区、Boss场）\r\n+  - **探索引导（示例）**：远处一束光/窗缝漏光/光斑落点 = “目标方向”（少用箭头）\r\n+- **烟雾**：雾 / 尘 / 雨雪 / 飘絮粒子/ 虫群/ 鸟群 / 云雾 / 烟雾 / 雾霾 → 空气感 + 深度层次\r\n+- **景**：形体 / 留白 / 层次 / 遮挡 / 景深 / 远景雾化 / 景深 / 远景雾化 → 可读性 + 叙事证据\r\n+- **运镜**：镜头节奏 / 构图变化 / 镜头移动 / 镜头切换 / 镜头抖动 / 镜头旋转 / 镜头拉近 / 镜头拉远 → 信息投放顺序（游戏里对应：视角/镜头/玩家路径节奏）\r\n+- **人**：动作 / 停顿 / 剪影 / 表情 / 姿态 / 动作 / 停顿 / 剪影 / 表情 / 姿态 → 情绪锚点（游戏里对应：玩家行为反馈/敌我态势）\r\n+- **音**：底噪 + 事件 + 反馈 / 音效 / 音效设计 / 音效 / 音效设计 → 氛围 + 提示 + 叙事补全\r\n+\r\n+### 从胡金铨画面迁移到游戏的 5 个高性价比细节\r\n+\r\n+1. **明暗大块面优先**：2–3 个明暗层次先定情绪与空间，细节可以少。\r\n+2. **留白就是内容**：雾/天空/空地/远山的“空”＝寂静、距离、未知。\r\n+3. **剪影可读性**：先看“形”，再看“细”；战斗和夜景尤其重要。\r\n+4. **光束 + 烟雾**：空气结构可见化，同时天然形成引导线（无 UI 导航）。\r\n+5. **遮挡 + 远景雾化**：前景遮挡 + 中景主体 + 远景降饱和/雾化 = 低成本纵深。\r\n+\r\n+---\r\n+\r\n+![环境表现设计理念分析](环境/Attached_image.png)\r\n+![环境表现设计理念分析](环境/Attached_image1.png)\r\n+![环境表现设计理念分析](环境/Attached_image2.png)\r\n+![环境表现设计理念分析](环境/Attached_image3.png)\r\n+![环境表现设计理念分析](环境/Attached_image4.png)\r\n+\r\n+## 环境叙事-落地\r\n+\r\n+> 每做一个新场景，至少交付下面 5 条；做不到就先别加“精细材质”。\r\n+\r\n+- **静态基底**：形体清晰、可读（不追求精细）。\r\n+- **动态一层**：树/草/旗/水面任一“活的动效”。\r\n+- **音效一层**：底噪（风/虫/水/城镇）+ 一条机制反馈（脚步/草/水/火）。\r\n+- **光照一层**：主光 + 明暗对比（至少能引导一处重点）。\r\n+- **后处理一层**：统一色调（冷/暖/压暗/对比度）让风格收敛。\r\n+\r\n+---\r\n+\r\n+## 环境叙事-交互反馈\r\n+\r\n+###  <font color=\"#4a7372\"> \"水\"  </font>\r\n+\r\n+**注重水的物理，而不是水的表现，保证玩家能读懂水的状态，水物理是拓展玩法基础**\r\n+\r\n+\r\n+**核心思维**：水的价值来自“玩法机制”，视觉只要“能读懂”。\r\n+\r\n+- **区域**：浅水/深水/危险/安全（颜色/纹理即可区分）\r\n+- **状态**：平静/波浪/结冰/污染/魔法（用动效或贴图变化表达）\r\n+- **交互反馈（尽量全面）**：\r\n+  - **移动**：减速/阻尼/额外行动点消耗/滑行（冰）/打滑（泥）/无法通行（深水）\r\n+  - **战斗/元素联动**：导电（雷范围/伤害变化）/冻结（冰封地形）/蒸汽（火+水：遮挡视野/灼伤）/污染（持续DOT/减益）/净化（解除负面）\r\n+  - **物理/环境**：浮力（漂浮物/尸体）/冲刷（河流推力）/沉没（重量阈值）/落水（摔落/眩晕）/溺水（窒息计时）\r\n+  - **探索/交互**：涉水声暴露/潜行加成（浅水草丛）/可采集（水草/鱼/药）/隐藏通道（浅滩/暗流）/机关（水位/闸门）\r\n+  - **表现层**：踩水声/波纹/水花/泡沫/水迹（湿身、脚印）、水面反光（够用即可）\r\n+  - **生存/代价（可选）**：体温流失（寒水）/疲劳消耗（逆流）/疾病或感染（污水）/装备受潮（易燃/失灵）/视野折射（误判距离）\r\n+- **机制绑定（示例）**：\r\n+  - 移动：行动点消耗、路径限制\r\n+  - 战斗：水 + 雷/冰/火（范围/状态/遮挡）\r\n+  - 探索：隐藏/资源/机关\r\n+\r\n+![环境表现设计理念分析](环境/水.png)\r\n+\r\n+---\r\n+\r\n+###  <font color=\"#5c4eb1\"> \"音\"  </font>\r\n+\r\n+**核心思维**：音效要支持玩法（提示/反馈/引导）及氛围营造，其次才是“好听”。\r\n+\r\n+- **底噪（氛围）**：风/虫/水/城镇人声（让场景“活”）\r\n+- **事件提示（引导）**：远处怪、机关、目标区域（方向性/距离衰减）\r\n+- **交互反馈（规则，尽量全面）**：\r\n+  - **脚步材质**：木/石/泥/草/雪/金属/沙（可读“地形”）\r\n+  - **水相关**：踩水/涉水/落水/游泳（可读“水位与风险”）\r\n+  - **植被/布料**：草动/树叶摩擦/旗帜拍打（可读“风与动向”）\r\n+  - **火与能量**：火焰噼啪/熄灭/爆燃、法术嗡鸣（可读“状态变化”）\r\n+  - **交互与UI替代**：开门/拾取/机关启动/宝箱（确认反馈）\r\n+  - **危险提示**：远处吼叫/脚步逼近/低频轰鸣（提前预警与引导）\r\n+  - **状态提示**：湿/冻/燃/毒/流血/诅咒（用“音色差异”让玩家听出状态）\r\n+  - **地形危险**：塌陷/碎石滚落/冰裂/泥陷（用预警音提示“将要发生”）\r\n+---\r\n+\r\n+###  <font color=\"#f57f17\"> \"光\"  </font>\r\n+\r\n+**核心思维**：光源的三个作用——**玩法机制、氛围营造、地图引导**。\r\n+\r\n+#### 光源的地图引导（最重要）\r\n+\r\n+- **明暗**：亮=重要/安全，暗=隐藏/危险（按你游戏规则定义）\r\n+- **颜色**：暖=安全/人类活动；冷=神秘/异界；红=危险/战斗\r\n+- **动态**：闪烁/移动/渐变＝吸引注意力、指示方向\r\n+\r\n+#### 光源的“规则提示”（不涉及实现）\r\n+\r\n+- **安全/可停留**：暖色/稳定/柔和衰减（营地、神龛、旅店、路灯聚光）\r\n+- **存档/重生/恢复**：更强的“仪式感光”（符文、光晕、聚光、点亮音）让玩家无需UI也能理解\r\n+- **危险/警戒**：红光/逆光剪影/闪烁/强对比（敌巢、Boss、陷阱区）\r\n+- **禁入/损伤**：黑光/低饱和/异常闪烁（诅咒区、污染区、精神压迫区）\r\n+\r\n+#### 光源系统的分类\r\n+\r\n+1. **自然光源（环境光源）**\r\n+   - 白天：太阳光、天空光、云层遮挡、轻反射\r\n+   - 黑夜：月光、星光、弱环境光\r\n+2. **人工光源（交互光源）**\r\n+   - 火把（玩家）、灯笼/火堆（场景）、魔法光（技能）\r\n+3. **玩法光源（机制光源）**\r\n+   - 视野/隐藏/战斗/探索（与规则绑定，优先级最高）\r\n+\r\n+#### 技术实现（够用即可）\r\n+\r\n+- **基础**：Directional Light + 阴影 + 简单后处理调色\r\n+- **可选增强**：动态时间、引导光源标记、少量光晕/粒子\r\n+\r\n+![环境表现设计理念分析](环境/attached_image6.png)\r\n+![环境表现设计理念分析](环境/attached_image7.png)\r\n+![环境表现设计理念分析](环境/attached_image8.png)\r\n"
                },
                {
                    "date": 1766137235577,
                    "content": "Index: \n===================================================================\n--- \n+++ \n@@ -138,152 +138,4 @@\n \r\n ![环境表现设计理念分析](环境/attached_image6.png)\r\n ![环境表现设计理念分析](环境/attached_image7.png)\r\n ![环境表现设计理念分析](环境/attached_image8.png)\r\n-# 环境表现设计理念分析（可一眼扫懂版）\r\n-\r\n-## 一句话结论\r\n-\r\n-**环境表现不是“堆美术”，而是用一套可复用的元素（光 / 动效 / 烟雾粒子 / 音 / 场景结构）去完成：引导、反馈、氛围，并尽量与玩法规则绑定。**\r\n-\r\n----\r\n-\r\n-## 核心原理（最重要的 3 件事）\r\n-\r\n-- **引导**：玩家不用 UI 也知道“往哪走、哪里重要、哪里危险”。（明暗对比 / 色温 / 方向性音效 / 动态吸引点）\r\n-- **反馈**：玩家的行为会被环境回应，让世界“活”。（脚步/草动/水波/火光变化/粒子散射）\r\n-- **氛围**：玩家能感受到“这里是什么地方、此刻是什么情绪”。（冷暖、留白、空气感、音景层次）\r\n-\r\n-> 判断标准：**不看 UI、不读字，玩家能否靠环境完成“导航 + 理解 + 感受”。**\r\n-\r\n----\r\n-\r\n-## 环境叙事-公式\r\n-\r\n-### 氛围公式（胡金铨）\r\n-\r\n-#### 美的氛围 = 光 + 烟雾 + 景 + 运镜 + 人 + 音\r\n-\r\n-- **光**：明暗 / 色温 / 聚焦 / 位置 / 光斑 / 光晕 / 光影 → 定调 + 引导 + 规则提示\r\n-  - **安全/存档/恢复（示例）**：暖光/稳定光源/聚光范围 = “安全锚点”（篝火、灯笼、神龛、阵法、营地）\r\n-  - **危险/禁入（示例）**：偏红/闪烁/逆光剪影/强对比 = “风险提示”（敌巢、陷阱区、Boss场）\r\n-  - **探索引导（示例）**：远处一束光/窗缝漏光/光斑落点 = “目标方向”（少用箭头）\r\n-- **烟雾**：雾 / 尘 / 雨雪 / 飘絮粒子/ 虫群/ 鸟群 / 云雾 / 烟雾 / 雾霾 → 空气感 + 深度层次\r\n-- **景**：形体 / 留白 / 层次 / 遮挡 / 景深 / 远景雾化 / 景深 / 远景雾化 → 可读性 + 叙事证据\r\n-- **运镜**：镜头节奏 / 构图变化 / 镜头移动 / 镜头切换 / 镜头抖动 / 镜头旋转 / 镜头拉近 / 镜头拉远 → 信息投放顺序（游戏里对应：视角/镜头/玩家路径节奏）\r\n-- **人**：动作 / 停顿 / 剪影 / 表情 / 姿态 / 动作 / 停顿 / 剪影 / 表情 / 姿态 → 情绪锚点（游戏里对应：玩家行为反馈/敌我态势）\r\n-- **音**：底噪 + 事件 + 反馈 / 音效 / 音效设计 / 音效 / 音效设计 → 氛围 + 提示 + 叙事补全\r\n-\r\n-### 从胡金铨画面迁移到游戏的 5 个高性价比细节\r\n-\r\n-1. **明暗大块面优先**：2–3 个明暗层次先定情绪与空间，细节可以少。\r\n-2. **留白就是内容**：雾/天空/空地/远山的“空”＝寂静、距离、未知。\r\n-3. **剪影可读性**：先看“形”，再看“细”；战斗和夜景尤其重要。\r\n-4. **光束 + 烟雾**：空气结构可见化，同时天然形成引导线（无 UI 导航）。\r\n-5. **遮挡 + 远景雾化**：前景遮挡 + 中景主体 + 远景降饱和/雾化 = 低成本纵深。\r\n-\r\n----\r\n-\r\n-![环境表现设计理念分析](环境/Attached_image.png)\r\n-![环境表现设计理念分析](环境/Attached_image1.png)\r\n-![环境表现设计理念分析](环境/Attached_image2.png)\r\n-![环境表现设计理念分析](环境/Attached_image3.png)\r\n-![环境表现设计理念分析](环境/Attached_image4.png)\r\n-\r\n-## 环境叙事-落地\r\n-\r\n-> 每做一个新场景，至少交付下面 5 条；做不到就先别加“精细材质”。\r\n-\r\n-- **静态基底**：形体清晰、可读（不追求精细）。\r\n-- **动态一层**：树/草/旗/水面任一“活的动效”。\r\n-- **音效一层**：底噪（风/虫/水/城镇）+ 一条机制反馈（脚步/草/水/火）。\r\n-- **光照一层**：主光 + 明暗对比（至少能引导一处重点）。\r\n-- **后处理一层**：统一色调（冷/暖/压暗/对比度）让风格收敛。\r\n-\r\n----\r\n-\r\n-## 环境叙事-交互反馈\r\n-\r\n-###  <font color=\"#4a7372\"> \"水\"  </font>\r\n-\r\n-**注重水的物理，而不是水的表现，保证玩家能读懂水的状态，水物理是拓展玩法基础**\r\n-\r\n-\r\n-**核心思维**：水的价值来自“玩法机制”，视觉只要“能读懂”。\r\n-\r\n-- **区域**：浅水/深水/危险/安全（颜色/纹理即可区分）\r\n-- **状态**：平静/波浪/结冰/污染/魔法（用动效或贴图变化表达）\r\n-- **交互反馈（尽量全面）**：\r\n-  - **移动**：减速/阻尼/额外行动点消耗/滑行（冰）/打滑（泥）/无法通行（深水）\r\n-  - **战斗/元素联动**：导电（雷范围/伤害变化）/冻结（冰封地形）/蒸汽（火+水：遮挡视野/灼伤）/污染（持续DOT/减益）/净化（解除负面）\r\n-  - **物理/环境**：浮力（漂浮物/尸体）/冲刷（河流推力）/沉没（重量阈值）/落水（摔落/眩晕）/溺水（窒息计时）\r\n-  - **探索/交互**：涉水声暴露/潜行加成（浅水草丛）/可采集（水草/鱼/药）/隐藏通道（浅滩/暗流）/机关（水位/闸门）\r\n-  - **表现层**：踩水声/波纹/水花/泡沫/水迹（湿身、脚印）、水面反光（够用即可）\r\n-  - **生存/代价（可选）**：体温流失（寒水）/疲劳消耗（逆流）/疾病或感染（污水）/装备受潮（易燃/失灵）/视野折射（误判距离）\r\n-- **机制绑定（示例）**：\r\n-  - 移动：行动点消耗、路径限制\r\n-  - 战斗：水 + 雷/冰/火（范围/状态/遮挡）\r\n-  - 探索：隐藏/资源/机关\r\n-\r\n-![环境表现设计理念分析](环境/水.png)\r\n-\r\n----\r\n-\r\n-###  <font color=\"#5c4eb1\"> \"音\"  </font>\r\n-\r\n-**核心思维**：音效要支持玩法（提示/反馈/引导）及氛围营造，其次才是“好听”。\r\n-\r\n-- **底噪（氛围）**：风/虫/水/城镇人声（让场景“活”）\r\n-- **事件提示（引导）**：远处怪、机关、目标区域（方向性/距离衰减）\r\n-- **交互反馈（规则，尽量全面）**：\r\n-  - **脚步材质**：木/石/泥/草/雪/金属/沙（可读“地形”）\r\n-  - **水相关**：踩水/涉水/落水/游泳（可读“水位与风险”）\r\n-  - **植被/布料**：草动/树叶摩擦/旗帜拍打（可读“风与动向”）\r\n-  - **火与能量**：火焰噼啪/熄灭/爆燃、法术嗡鸣（可读“状态变化”）\r\n-  - **交互与UI替代**：开门/拾取/机关启动/宝箱（确认反馈）\r\n-  - **危险提示**：远处吼叫/脚步逼近/低频轰鸣（提前预警与引导）\r\n-  - **状态提示**：湿/冻/燃/毒/流血/诅咒（用“音色差异”让玩家听出状态）\r\n-  - **地形危险**：塌陷/碎石滚落/冰裂/泥陷（用预警音提示“将要发生”）\r\n----\r\n-\r\n-###  <font color=\"#f57f17\"> \"光\"  </font>\r\n-\r\n-**核心思维**：光源的三个作用——**玩法机制、氛围营造、地图引导**。\r\n-\r\n-#### 光源的地图引导（最重要）\r\n-\r\n-- **明暗**：亮=重要/安全，暗=隐藏/危险（按你游戏规则定义）\r\n-- **颜色**：暖=安全/人类活动；冷=神秘/异界；红=危险/战斗\r\n-- **动态**：闪烁/移动/渐变＝吸引注意力、指示方向\r\n-\r\n-#### 光源的“规则提示”（不涉及实现）\r\n-\r\n-- **安全/可停留**：暖色/稳定/柔和衰减（营地、神龛、旅店、路灯聚光）\r\n-- **存档/重生/恢复**：更强的“仪式感光”（符文、光晕、聚光、点亮音）让玩家无需UI也能理解\r\n-- **危险/警戒**：红光/逆光剪影/闪烁/强对比（敌巢、Boss、陷阱区）\r\n-- **禁入/损伤**：黑光/低饱和/异常闪烁（诅咒区、污染区、精神压迫区）\r\n-\r\n-#### 光源系统的分类\r\n-\r\n-1. **自然光源（环境光源）**\r\n-   - 白天：太阳光、天空光、云层遮挡、轻反射\r\n-   - 黑夜：月光、星光、弱环境光\r\n-2. **人工光源（交互光源）**\r\n-   - 火把（玩家）、灯笼/火堆（场景）、魔法光（技能）\r\n-3. **玩法光源（机制光源）**\r\n-   - 视野/隐藏/战斗/探索（与规则绑定，优先级最高）\r\n-\r\n-#### 技术实现（够用即可）\r\n-\r\n-- **基础**：Directional Light + 阴影 + 简单后处理调色\r\n-- **可选增强**：动态时间、引导光源标记、少量光晕/粒子\r\n-\r\n-![环境表现设计理念分析](环境/attached_image6.png)\r\n-![环境表现设计理念分析](环境/attached_image7.png)\r\n-![环境表现设计理念分析](环境/attached_image8.png)\r\n----\r\n-\r\n-## 你当前这套方法论的优势（给未来的自己）\r\n-\r\n-- **可拓展**：同一套“光/音/动效/雾/留白/剪影”能无限复用，风格越做越统一。\r\n-- **可控成本**：不依赖高精度模型，也能做出“有气”的场景。\r\n-- **可服务玩法**：环境表现直接成为玩法的一部分（引导/反馈/规则）。\r\n"
                },
                {
                    "date": 1766137268297,
                    "content": "Index: \n===================================================================\n--- \n+++ \n@@ -66,9 +66,9 @@\n \r\n **注重水的物理，而不是水的表现，保证玩家能读懂水的状态，水物理是拓展玩法基础**\r\n \r\n \r\n-**核心思维**：水的价值来自“玩法机制”，视觉只要“能读懂”。\r\n+**核心思维**：水的价值来自“玩法机制”，视觉只需“能读懂”。\r\n \r\n - **区域**：浅水/深水/危险/安全（颜色/纹理即可区分）\r\n - **状态**：平静/波浪/结冰/污染/魔法（用动效或贴图变化表达）\r\n - **交互反馈（尽量全面）**：\r\n"
                },
                {
                    "date": 1766137276475,
                    "content": "Index: \n===================================================================\n--- \n+++ \n@@ -70,9 +70,9 @@\n **核心思维**：水的价值来自“玩法机制”，视觉只需“能读懂”。\r\n \r\n - **区域**：浅水/深水/危险/安全（颜色/纹理即可区分）\r\n - **状态**：平静/波浪/结冰/污染/魔法（用动效或贴图变化表达）\r\n-- **交互反馈（尽量全面）**：\r\n+- **交互反馈**：\r\n   - **移动**：减速/阻尼/额外行动点消耗/滑行（冰）/打滑（泥）/无法通行（深水）\r\n   - **战斗/元素联动**：导电（雷范围/伤害变化）/冻结（冰封地形）/蒸汽（火+水：遮挡视野/灼伤）/污染（持续DOT/减益）/净化（解除负面）\r\n   - **物理/环境**：浮力（漂浮物/尸体）/冲刷（河流推力）/沉没（重量阈值）/落水（摔落/眩晕）/溺水（窒息计时）\r\n   - **探索/交互**：涉水声暴露/潜行加成（浅水草丛）/可采集（水草/鱼/药）/隐藏通道（浅滩/暗流）/机关（水位/闸门）\r\n"
                },
                {
                    "date": 1766137288404,
                    "content": "Index: \n===================================================================\n--- \n+++ \n@@ -92,9 +92,9 @@\n **核心思维**：音效要支持玩法（提示/反馈/引导）及氛围营造，其次才是“好听”。\r\n \r\n - **底噪（氛围）**：风/虫/水/城镇人声（让场景“活”）\r\n - **事件提示（引导）**：远处怪、机关、目标区域（方向性/距离衰减）\r\n-- **交互反馈（规则，尽量全面）**：\r\n+- **交互反馈**：\r\n   - **脚步材质**：木/石/泥/草/雪/金属/沙（可读“地形”）\r\n   - **水相关**：踩水/涉水/落水/游泳（可读“水位与风险”）\r\n   - **植被/布料**：草动/树叶摩擦/旗帜拍打（可读“风与动向”）\r\n   - **火与能量**：火焰噼啪/熄灭/爆燃、法术嗡鸣（可读“状态变化”）\r\n"
                },
                {
                    "date": 1766137323102,
                    "content": "Index: \n===================================================================\n--- \n+++ \n@@ -1,5 +1,5 @@\n-# 环境表现设计理念分析（可一眼扫懂版）\r\n+# 环境表现设计理念分析\r\n \r\n ## 一句话结论\r\n \r\n **环境表现不是“堆美术”，而是用一套可复用的元素（光 / 动效 / 烟雾粒子 / 音 / 场景结构）去完成：引导、反馈、氛围，并尽量与玩法规则绑定。**\r\n"
                },
                {
                    "date": 1766137582345,
                    "content": "Index: \n===================================================================\n--- \n+++ \n@@ -103,8 +103,23 @@\n   - **状态提示**：湿/冻/燃/毒/流血/诅咒（用“音色差异”让玩家听出状态）\r\n   - **地形危险**：塌陷/碎石滚落/冰裂/泥陷（用预警音提示“将要发生”）\r\n ---\r\n \r\n+###  <font color=\"#4caf50\"> \"风\"  </font>\r\n+\r\n+**核心思维**：风是“动态与方向”的载体——用风把场景变活，并把“方向/危险/时机/代价”变成可读信息。\r\n+\r\n+- **可读信号（表现）**：草木摆动方向、旗帜/布条、尘雾/飘絮、风声强弱与方向\r\n+- **交互反馈（尽量全面）**：\r\n+  - **移动/探索**：逆风更慢/顺风更快/攀爬更难/跳跃落点偏移（可选）；强风区域限制通行或强制位移；风向提示“通道/出口/空旷区”\r\n+  - **战斗/远程**：箭矢/投掷偏转；烟雾/毒雾/火势随风扩散；风系技能推拉/击退/打断；火+风=助燃/蔓延；雾+风=驱散/开视野\r\n+  - **潜行/感知**：风声掩盖脚步（潜行加成）或吹动植被暴露位置（可选）；风铃/旗帜作为“警戒物”（触发敌人注意）\r\n+  - **环境/机关**：风车/风铃/门扇/帘幕触发；需要“顺风点火/点灯”；风向改变触发谜题或路径开放\r\n+  - **生存/代价（可选）**：寒风体温流失；沙尘风降低命中/视野；暴风雨降低行动/命中与持续伤害（按项目取舍）\r\n+  - **表现层**：草木/衣摆/旗帜摆动、尘雾/落叶/飘絮粒子、风声层次（微风/强风/暴风）\r\n+\r\n+---\r\n+\r\n ###  <font color=\"#f57f17\"> \"光\"  </font>\r\n \r\n **核心思维**：光源的三个作用——**玩法机制、氛围营造、地图引导**。\r\n \r\n"
                },
                {
                    "date": 1766137633842,
                    "content": "Index: \n===================================================================\n--- \n+++ \n@@ -61,13 +61,12 @@\n ---\r\n \r\n ## 环境叙事-交互反馈\r\n \r\n-###  <font color=\"#4a7372\"> \"水\"  </font>\r\n+### 水\r\n \r\n-**注重水的物理，而不是水的表现，保证玩家能读懂水的状态，水物理是拓展玩法基础**\r\n+注重水的物理，而不是水的表现；保证玩家能读懂水的状态，水的“物理/规则”是拓展玩法的基础。\r\n \r\n-\r\n **核心思维**：水的价值来自“玩法机制”，视觉只需“能读懂”。\r\n \r\n - **区域**：浅水/深水/危险/安全（颜色/纹理即可区分）\r\n - **状态**：平静/波浪/结冰/污染/魔法（用动效或贴图变化表达）\r\n@@ -86,9 +85,9 @@\n ![环境表现设计理念分析](环境/水.png)\r\n \r\n ---\r\n \r\n-###  <font color=\"#5c4eb1\"> \"音\"  </font>\r\n+### 音\r\n \r\n **核心思维**：音效要支持玩法（提示/反馈/引导）及氛围营造，其次才是“好听”。\r\n \r\n - **底噪（氛围）**：风/虫/水/城镇人声（让场景“活”）\r\n@@ -101,11 +100,12 @@\n   - **交互与UI替代**：开门/拾取/机关启动/宝箱（确认反馈）\r\n   - **危险提示**：远处吼叫/脚步逼近/低频轰鸣（提前预警与引导）\r\n   - **状态提示**：湿/冻/燃/毒/流血/诅咒（用“音色差异”让玩家听出状态）\r\n   - **地形危险**：塌陷/碎石滚落/冰裂/泥陷（用预警音提示“将要发生”）\r\n+\r\n ---\r\n \r\n-###  <font color=\"#4caf50\"> \"风\"  </font>\r\n+### 风\r\n \r\n **核心思维**：风是“动态与方向”的载体——用风把场景变活，并把“方向/危险/时机/代价”变成可读信息。\r\n \r\n - **可读信号（表现）**：草木摆动方向、旗帜/布条、尘雾/飘絮、风声强弱与方向\r\n@@ -118,9 +118,9 @@\n   - **表现层**：草木/衣摆/旗帜摆动、尘雾/落叶/飘絮粒子、风声层次（微风/强风/暴风）\r\n \r\n ---\r\n \r\n-###  <font color=\"#f57f17\"> \"光\"  </font>\r\n+### 光\r\n \r\n **核心思维**：光源的三个作用——**玩法机制、氛围营造、地图引导**。\r\n \r\n #### 光源的地图引导（最重要）\r\n"
                },
                {
                    "date": 1766137661945,
                    "content": "Index: \n===================================================================\n--- \n+++ \n@@ -61,12 +61,13 @@\n ---\r\n \r\n ## 环境叙事-交互反馈\r\n \r\n-### 水\r\n+###  <font color=\"#4a7372\"> \"水\"  </font>\r\n \r\n-注重水的物理，而不是水的表现；保证玩家能读懂水的状态，水的“物理/规则”是拓展玩法的基础。\r\n+**注重水的物理，而不是水的表现，保证玩家能读懂水的状态，水物理是拓展玩法基础**\r\n \r\n+\r\n **核心思维**：水的价值来自“玩法机制”，视觉只需“能读懂”。\r\n \r\n - **区域**：浅水/深水/危险/安全（颜色/纹理即可区分）\r\n - **状态**：平静/波浪/结冰/污染/魔法（用动效或贴图变化表达）\r\n@@ -85,9 +86,12 @@\n ![环境表现设计理念分析](环境/水.png)\r\n \r\n ---\r\n \r\n-### 音\r\n+![环境表现设计理念分析](环境/attached_image6.png)\r\n+![环境表现设计理念分析](环境/attached_image7.png)\r\n+![环境表现设计理念分析](环境/attached_image8.png)\r\n+###  <font color=\"#5c4eb1\"> \"音\"  </font>\r\n \r\n **核心思维**：音效要支持玩法（提示/反馈/引导）及氛围营造，其次才是“好听”。\r\n \r\n - **底噪（氛围）**：风/虫/水/城镇人声（让场景“活”）\r\n@@ -100,12 +104,11 @@\n   - **交互与UI替代**：开门/拾取/机关启动/宝箱（确认反馈）\r\n   - **危险提示**：远处吼叫/脚步逼近/低频轰鸣（提前预警与引导）\r\n   - **状态提示**：湿/冻/燃/毒/流血/诅咒（用“音色差异”让玩家听出状态）\r\n   - **地形危险**：塌陷/碎石滚落/冰裂/泥陷（用预警音提示“将要发生”）\r\n-\r\n ---\r\n \r\n-### 风\r\n+###  <font color=\"#4caf50\"> \"风\"  </font>\r\n \r\n **核心思维**：风是“动态与方向”的载体——用风把场景变活，并把“方向/危险/时机/代价”变成可读信息。\r\n \r\n - **可读信号（表现）**：草木摆动方向、旗帜/布条、尘雾/飘絮、风声强弱与方向\r\n@@ -118,9 +121,9 @@\n   - **表现层**：草木/衣摆/旗帜摆动、尘雾/落叶/飘絮粒子、风声层次（微风/强风/暴风）\r\n \r\n ---\r\n \r\n-### 光\r\n+###  <font color=\"#f57f17\"> \"光\"  </font>\r\n \r\n **核心思维**：光源的三个作用——**玩法机制、氛围营造、地图引导**。\r\n \r\n #### 光源的地图引导（最重要）\r\n@@ -150,7 +153,4 @@\n \r\n - **基础**：Directional Light + 阴影 + 简单后处理调色\r\n - **可选增强**：动态时间、引导光源标记、少量光晕/粒子\r\n \r\n-![环境表现设计理念分析](环境/attached_image6.png)\r\n-![环境表现设计理念分析](环境/attached_image7.png)\r\n-![环境表现设计理念分析](环境/attached_image8.png)\r\n"
                },
                {
                    "date": 1766137667557,
                    "content": "Index: \n===================================================================\n--- \n+++ \n@@ -86,11 +86,8 @@\n ![环境表现设计理念分析](环境/水.png)\r\n \r\n ---\r\n \r\n-![环境表现设计理念分析](环境/attached_image6.png)\r\n-![环境表现设计理念分析](环境/attached_image7.png)\r\n-![环境表现设计理念分析](环境/attached_image8.png)\r\n ###  <font color=\"#5c4eb1\"> \"音\"  </font>\r\n \r\n **核心思维**：音效要支持玩法（提示/反馈/引导）及氛围营造，其次才是“好听”。\r\n \r\n@@ -153,4 +150,7 @@\n \r\n - **基础**：Directional Light + 阴影 + 简单后处理调色\r\n - **可选增强**：动态时间、引导光源标记、少量光晕/粒子\r\n \r\n+![环境表现设计理念分析](环境/attached_image6.png)\r\n+![环境表现设计理念分析](环境/attached_image7.png)\r\n+![环境表现设计理念分析](环境/attached_image8.png)\r\n"
                },
                {
                    "date": 1766137903819,
                    "content": "Index: \n===================================================================\n--- \n+++ \n@@ -153,4 +153,48 @@\n \r\n ![环境表现设计理念分析](环境/attached_image6.png)\r\n ![环境表现设计理念分析](环境/attached_image7.png)\r\n ![环境表现设计理念分析](环境/attached_image8.png)\r\n+\r\n+---\r\n+\r\n+###  <font color=\"#2196f3\"> \"雨\"  </font>\r\n+\r\n+**核心思维**：雨是“持续状态 + 地形变化”的载体——用雨把场景变湿，并把“视野/移动/生存/元素联动”变成可读信息。\r\n+\r\n+- **可读信号（表现）**：雨滴/雨幕、水坑/积水、湿身/水迹、雨声层次（小雨/中雨/暴雨）\r\n+- **交互反馈（尽量全面）**：\r\n+  - **移动/探索**：地面打滑/减速；水坑形成（浅水区）；攀爬/跳跃难度增加；雨声掩盖脚步（潜行加成）\r\n+  - **战斗/元素联动**：远程命中降低（视野模糊/能见度）；火+雨=熄灭/蒸汽（遮挡视野/灼伤）；雷+雨=导电范围扩大/伤害增强；冰+雨=结冰/滑行\r\n+  - **视野/感知**：能见度降低/视野模糊；雨幕遮挡视线；雨声干扰听觉判断\r\n+  - **生存/代价（可选）**：体温流失（寒雨）；装备受潮（易燃/失灵/重量增加）；疲劳消耗（持续移动）；疾病或感染（污染雨）\r\n+  - **环境/机关**：水位上涨触发机关；需要“避雨/遮雨”机制；雨停后水坑残留（地形变化）\r\n+  - **表现层**：雨滴粒子/雨幕、水坑/积水、湿身/水迹、雨声层次（小雨/中雨/暴雨）、闪电配合（可选）\r\n+\r\n+---\r\n+\r\n+###  <font color=\"#ffeb3b\"> \"雷\"  </font>\r\n+\r\n+**核心思维**：雷是“瞬间爆发 + 连锁反应”的载体——用雷把危险可视化，并把“预警/伤害/导电/连锁”变成可读信息。\r\n+\r\n+- **可读信号（表现）**：闪电/雷光、雷声/轰鸣、电荷粒子/电火花、预警音/闪烁提示\r\n+- **交互反馈（尽量全面）**：\r\n+  - **战斗/元素联动**：直接伤害/范围伤害；水+雷=导电范围扩大/伤害增强/连锁传导；金属+雷=吸引/增强/传导；火+雷=爆燃/范围扩大\r\n+  - **预警/引导**：闪电提前照亮区域（引导/暴露）；雷声提示“危险区域/即将落雷”；电荷积累提示（可读“即将爆发”）\r\n+  - **环境/机关**：雷击触发机关/开关；需要“避雷/引雷”机制；雷击点燃/破坏物体\r\n+  - **移动/探索**：雷击区域限制通行；需要“等待时机/快速通过”；雷击暴露隐藏通道/机关\r\n+  - **表现层**：闪电/雷光、雷声/轰鸣、电荷粒子/电火花、预警音/闪烁提示、连锁传导效果（可选）\r\n+\r\n+---\r\n+\r\n+###  <font color=\"#e3f2fd\"> \"雪\"  </font>\r\n+\r\n+**核心思维**：雪是“地形覆盖 + 状态叠加”的载体——用雪把场景变白，并把“移动/视野/温度/元素联动”变成可读信息。\r\n+\r\n+- **可读信号（表现）**：雪花/雪幕、积雪/雪堆、脚印/痕迹、雪声（踩雪/落雪）\r\n+- **交互反馈（尽量全面）**：\r\n+  - **移动/探索**：减速/额外行动点消耗；深雪限制通行；脚印暴露行踪（潜行惩罚）；滑行（冰面）\r\n+  - **战斗/元素联动**：火+雪=融化/蒸汽（遮挡视野/灼伤）；雷+雪=导电减弱/范围缩小；冰+雪=冻结/滑行/伤害增强\r\n+  - **视野/感知**：雪幕遮挡视线；能见度降低；雪地反光（可选：闪光/误判）\r\n+  - **生存/代价（可选）**：体温流失（持续）；疲劳消耗（深雪移动）；雪盲（视野受限/持续伤害）\r\n+  - **环境/机关**：积雪触发机关/开关；需要“扫雪/融雪”机制；雪堆形成障碍/掩体\r\n+  - **表现层**：雪花/雪幕、积雪/雪堆、脚印/痕迹、雪声（踩雪/落雪）、反光效果（够用即可）\r\n"
                },
                {
                    "date": 1766138007252,
                    "content": "Index: \n===================================================================\n--- \n+++ \n@@ -197,4 +197,19 @@\n   - **视野/感知**：雪幕遮挡视线；能见度降低；雪地反光（可选：闪光/误判）\r\n   - **生存/代价（可选）**：体温流失（持续）；疲劳消耗（深雪移动）；雪盲（视野受限/持续伤害）\r\n   - **环境/机关**：积雪触发机关/开关；需要“扫雪/融雪”机制；雪堆形成障碍/掩体\r\n   - **表现层**：雪花/雪幕、积雪/雪堆、脚印/痕迹、雪声（踩雪/落雪）、反光效果（够用即可）\r\n+\r\n+---\r\n+\r\n+###  <font color=\"#ff5722\"> \"火\"  </font>\r\n+\r\n+**核心思维**：火是“持续伤害 + 光照引导”的载体——用火把危险可视化，并把“伤害/视野/元素联动/环境交互”变成可读信息。\r\n+\r\n+- **可读信号（表现）**：火焰/火光、烟雾/灰烬、热浪/扭曲、火声（燃烧/噼啪/熄灭）\r\n+- **交互反馈（尽量全面）**：\r\n+  - **战斗/元素联动**：持续伤害/灼伤；水+火=熄灭/蒸汽（遮挡视野/灼伤）；风+火=助燃/蔓延/范围扩大；雷+火=爆燃/范围扩大；雪/冰+火=融化/蒸汽\r\n+  - **视野/引导**：火光提供照明（引导/安全锚点）；烟雾遮挡视线；热浪扭曲视野（可选）\r\n+  - **移动/探索**：火焰区域限制通行；需要“灭火/避火”机制；火焰点燃/破坏物体\r\n+  - **环境/机关**：火焰触发机关/开关；需要“点火/熄火”机制；火焰点燃/破坏障碍/掩体\r\n+  - **生存/代价（可选）**：灼伤持续伤害；体温上升（可选：过热/中暑）；装备易燃/损坏\r\n+  - **表现层**：火焰/火光、烟雾/灰烬、热浪/扭曲、火声（燃烧/噼啪/熄灭）、点燃/蔓延效果（够用即可）\r\n"
                },
                {
                    "date": 1766138191755,
                    "content": "Index: \n===================================================================\n--- \n+++ \n@@ -59,8 +59,40 @@\n - **后处理一层**：统一色调（冷/暖/压暗/对比度）让风格收敛。\r\n \r\n ---\r\n \r\n+## 环境叙事-元素选择原则\r\n+\r\n+> 如何选择/组合环境元素？如何判断优先级？\r\n+\r\n+### 选择原则（3个维度）\r\n+\r\n+1. **功能优先级**：先满足“引导/反馈/氛围”中的核心需求\r\n+   - **引导需求**：优先选“光/音/动态元素”（方向性/吸引点）\r\n+   - **反馈需求**：优先选“水/火/风/植被”（玩家行为可触发）\r\n+   - **氛围需求**：优先选“雾/烟/音/光”（情绪/空气感）\r\n+\r\n+2. **成本优先级**：先做“高性价比”元素\r\n+   - **低成本高效果**：光（后处理调色）、音（底噪+1条反馈）、风（粒子+摆动）\r\n+   - **中成本中效果**：水（动效+交互）、火（粒子+光照）、雨（粒子+音效）\r\n+   - **高成本需谨慎**：雷（特效+预警系统）、雪（地形变化+状态系统）\r\n+\r\n+3. **联动优先级**：优先选“可联动”元素\r\n+   - **核心联动链**：水↔火↔雷↔风（4元素互相影响）\r\n+   - **辅助联动**：雨+风、雪+风、火+风、雾+风\r\n+   - **独立元素**：光、音（可独立使用，也可配合其他）\r\n+\r\n+### 组合原则（2个规则）\r\n+\r\n+- **MVP组合**：光 + 音 + 1个动态元素（风/水/火/植被）= 基础氛围\r\n+- **扩展组合**：MVP + 1-2个联动元素（雨+风、火+风、水+雷）= 丰富交互\r\n+\r\n+### 判断标准\r\n+\r\n+> 问自己：**这个元素是否直接支持“引导/反馈/氛围”中的至少一个？如果只是“好看”，先不做。**\r\n+\r\n+---\r\n+\r\n ## 环境叙事-交互反馈\r\n \r\n ###  <font color=\"#4a7372\"> \"水\"  </font>\r\n \r\n"
                },
                {
                    "date": 1766138220539,
                    "content": "Index: \n===================================================================\n--- \n+++ \n@@ -244,4 +244,34 @@\n   - **移动/探索**：火焰区域限制通行；需要“灭火/避火”机制；火焰点燃/破坏物体\r\n   - **环境/机关**：火焰触发机关/开关；需要“点火/熄火”机制；火焰点燃/破坏障碍/掩体\r\n   - **生存/代价（可选）**：灼伤持续伤害；体温上升（可选：过热/中暑）；装备易燃/损坏\r\n   - **表现层**：火焰/火光、烟雾/灰烬、热浪/扭曲、火声（燃烧/噼啪/熄灭）、点燃/蔓延效果（够用即可）\r\n+\r\n+---\r\n+\r\n+###  <font color=\"#9e9e9e\"> \"雾/烟\"  </font>\r\n+\r\n+**核心思维**：雾/烟是“视野遮挡 + 空气感”的载体——用雾把空间分层，并把“隐藏/引导/深度/危险”变成可读信息。\r\n+\r\n+- **可读信号（表现）**：雾气/烟雾、能见度变化、深度层次、雾声（可选：风声/低鸣）\r\n+- **交互反馈（尽量全面）**：\r\n+  - **视野/感知**：能见度降低/视野模糊；雾中隐藏（潜行加成/敌人视野受限）；烟雾遮挡视线/标记位置\r\n+  - **移动/探索**：雾中迷失方向（可选：需要导航/标记）；浓雾限制通行；雾散/雾聚触发路径开放\r\n+  - **战斗/元素联动**：远程命中降低（视野模糊）；风+雾=驱散/开视野；火+雾=烟雾/遮挡增强；毒+雾=毒雾/持续伤害\r\n+  - **引导/氛围**：雾气形成“通道/出口”引导；浓雾=危险/未知；薄雾=神秘/氛围\r\n+  - **环境/机关**：雾气触发机关/开关；需要“驱雾/引雾”机制；雾气形成障碍/掩体\r\n+  - **表现层**：雾气/烟雾粒子、能见度渐变、深度层次、雾声（可选：风声/低鸣）、光在雾中的散射（够用即可）\r\n+\r\n+---\r\n+\r\n+###  <font color=\"#8bc34a\"> \"植被\"  </font>\r\n+\r\n+**核心思维**：植被是“动态反馈 + 地形交互”的载体——用植被把场景变活，并把“移动/隐藏/资源/风向”变成可读信息。\r\n+\r\n+- **可读信号（表现）**：草木摆动、植被状态（正常/枯萎/燃烧）、资源点（可采集）、风向指示\r\n+- **交互反馈（尽量全面）**：\r\n+  - **移动/探索**：草丛减速/额外行动点消耗；深草限制通行；植被形成障碍/掩体；踩踏暴露行踪（可选）\r\n+  - **潜行/隐藏**：草丛隐藏（潜行加成）；植被摆动暴露位置（可选：风/玩家移动触发）；植被遮挡视线\r\n+  - **战斗/元素联动**：植被燃烧（火+植被=蔓延/伤害）；植被导电（雷+植被=范围扩大/伤害增强）；植被冻结（冰+植被=减速/伤害）\r\n+  - **探索/交互**：可采集（草药/果实/木材）；植被触发机关/开关；需要“砍伐/清理”机制\r\n+  - **环境/反馈**：植被摆动指示风向；植被状态反映环境（枯萎=干旱/污染，茂盛=水源/安全）\r\n+  - **表现层**：草木摆动、植被状态变化、资源点标记、踩踏反馈（够用即可）\r\n"
                },
                {
                    "date": 1766138236170,
                    "content": "Index: \n===================================================================\n--- \n+++ \n@@ -97,13 +97,11 @@\n ###  <font color=\"#4a7372\"> \"水\"  </font>\r\n \r\n **注重水的物理，而不是水的表现，保证玩家能读懂水的状态，水物理是拓展玩法基础**\r\n \r\n-\r\n **核心思维**：水的价值来自“玩法机制”，视觉只需“能读懂”。\r\n \r\n-- **区域**：浅水/深水/危险/安全（颜色/纹理即可区分）\r\n-- **状态**：平静/波浪/结冰/污染/魔法（用动效或贴图变化表达）\r\n+- **区域/状态**（地形类元素特有）：浅水/深水/危险/安全（颜色/纹理即可区分）；平静/波浪/结冰/污染/魔法（用动效或贴图变化表达）\r\n - **交互反馈**：\r\n   - **移动**：减速/阻尼/额外行动点消耗/滑行（冰）/打滑（泥）/无法通行（深水）\r\n   - **战斗/元素联动**：导电（雷范围/伤害变化）/冻结（冰封地形）/蒸汽（火+水：遮挡视野/灼伤）/污染（持续DOT/减益）/净化（解除负面）\r\n   - **物理/环境**：浮力（漂浮物/尸体）/冲刷（河流推力）/沉没（重量阈值）/落水（摔落/眩晕）/溺水（窒息计时）\r\n"
                },
                {
                    "date": 1766138247383,
                    "content": "Index: \n===================================================================\n--- \n+++ \n@@ -234,8 +234,9 @@\n ###  <font color=\"#ff5722\"> \"火\"  </font>\r\n \r\n **核心思维**：火是“持续伤害 + 光照引导”的载体——用火把危险可视化，并把“伤害/视野/元素联动/环境交互”变成可读信息。\r\n \r\n+- **状态**：燃烧/熄灭/蔓延/爆燃（用动效或粒子变化表达）\r\n - **可读信号（表现）**：火焰/火光、烟雾/灰烬、热浪/扭曲、火声（燃烧/噼啪/熄灭）\r\n - **交互反馈（尽量全面）**：\r\n   - **战斗/元素联动**：持续伤害/灼伤；水+火=熄灭/蒸汽（遮挡视野/灼伤）；风+火=助燃/蔓延/范围扩大；雷+火=爆燃/范围扩大；雪/冰+火=融化/蒸汽\r\n   - **视野/引导**：火光提供照明（引导/安全锚点）；烟雾遮挡视线；热浪扭曲视野（可选）\r\n"
                },
                {
                    "date": 1766138254358,
                    "content": "Index: \n===================================================================\n--- \n+++ \n@@ -250,8 +250,9 @@\n ###  <font color=\"#9e9e9e\"> \"雾/烟\"  </font>\r\n \r\n **核心思维**：雾/烟是“视野遮挡 + 空气感”的载体——用雾把空间分层，并把“隐藏/引导/深度/危险”变成可读信息。\r\n \r\n+- **状态**：薄雾/浓雾/烟雾/毒雾（用粒子密度/颜色变化表达）\r\n - **可读信号（表现）**：雾气/烟雾、能见度变化、深度层次、雾声（可选：风声/低鸣）\r\n - **交互反馈（尽量全面）**：\r\n   - **视野/感知**：能见度降低/视野模糊；雾中隐藏（潜行加成/敌人视野受限）；烟雾遮挡视线/标记位置\r\n   - **移动/探索**：雾中迷失方向（可选：需要导航/标记）；浓雾限制通行；雾散/雾聚触发路径开放\r\n"
                },
                {
                    "date": 1766138264055,
                    "content": "Index: \n===================================================================\n--- \n+++ \n@@ -266,9 +266,10 @@\n ###  <font color=\"#8bc34a\"> \"植被\"  </font>\r\n \r\n **核心思维**：植被是“动态反馈 + 地形交互”的载体——用植被把场景变活，并把“移动/隐藏/资源/风向”变成可读信息。\r\n \r\n-- **可读信号（表现）**：草木摆动、植被状态（正常/枯萎/燃烧）、资源点（可采集）、风向指示\r\n+- **状态**：正常/枯萎/燃烧/冻结（用颜色/动效变化表达）\r\n+- **可读信号（表现）**：草木摆动、植被状态、资源点（可采集）、风向指示\r\n - **交互反馈（尽量全面）**：\r\n   - **移动/探索**：草丛减速/额外行动点消耗；深草限制通行；植被形成障碍/掩体；踩踏暴露行踪（可选）\r\n   - **潜行/隐藏**：草丛隐藏（潜行加成）；植被摆动暴露位置（可选：风/玩家移动触发）；植被遮挡视线\r\n   - **战斗/元素联动**：植被燃烧（火+植被=蔓延/伤害）；植被导电（雷+植被=范围扩大/伤害增强）；植被冻结（冰+植被=减速/伤害）\r\n"
                },
                {
                    "date": 1766138551551,
                    "content": "Index: \n===================================================================\n--- \n+++ \n@@ -57,40 +57,9 @@\n - **音效一层**：底噪（风/虫/水/城镇）+ 一条机制反馈（脚步/草/水/火）。\r\n - **光照一层**：主光 + 明暗对比（至少能引导一处重点）。\r\n - **后处理一层**：统一色调（冷/暖/压暗/对比度）让风格收敛。\r\n \r\n----\r\n \r\n-## 环境叙事-元素选择原则\r\n-\r\n-> 如何选择/组合环境元素？如何判断优先级？\r\n-\r\n-### 选择原则（3个维度）\r\n-\r\n-1. **功能优先级**：先满足“引导/反馈/氛围”中的核心需求\r\n-   - **引导需求**：优先选“光/音/动态元素”（方向性/吸引点）\r\n-   - **反馈需求**：优先选“水/火/风/植被”（玩家行为可触发）\r\n-   - **氛围需求**：优先选“雾/烟/音/光”（情绪/空气感）\r\n-\r\n-2. **成本优先级**：先做“高性价比”元素\r\n-   - **低成本高效果**：光（后处理调色）、音（底噪+1条反馈）、风（粒子+摆动）\r\n-   - **中成本中效果**：水（动效+交互）、火（粒子+光照）、雨（粒子+音效）\r\n-   - **高成本需谨慎**：雷（特效+预警系统）、雪（地形变化+状态系统）\r\n-\r\n-3. **联动优先级**：优先选“可联动”元素\r\n-   - **核心联动链**：水↔火↔雷↔风（4元素互相影响）\r\n-   - **辅助联动**：雨+风、雪+风、火+风、雾+风\r\n-   - **独立元素**：光、音（可独立使用，也可配合其他）\r\n-\r\n-### 组合原则（2个规则）\r\n-\r\n-- **MVP组合**：光 + 音 + 1个动态元素（风/水/火/植被）= 基础氛围\r\n-- **扩展组合**：MVP + 1-2个联动元素（雨+风、火+风、水+雷）= 丰富交互\r\n-\r\n-### 判断标准\r\n-\r\n-> 问自己：**这个元素是否直接支持“引导/反馈/氛围”中的至少一个？如果只是“好看”，先不做。**\r\n-\r\n ---\r\n \r\n ## 环境叙事-交互反馈\r\n \r\n"
                },
                {
                    "date": 1766138816714,
                    "content": "Index: \n===================================================================\n--- \n+++ \n@@ -47,8 +47,43 @@\n ![环境表现设计理念分析](环境/Attached_image2.png)\r\n ![环境表现设计理念分析](环境/Attached_image3.png)\r\n ![环境表现设计理念分析](环境/Attached_image4.png)\r\n \r\n+---\r\n+\r\n+## 环境叙事-设计哲学\r\n+\r\n+> **核心问题**：关注元素本身，不关注元素背后形成的根源，导致违和感。\r\n+\r\n+### 设计哲学对比\r\n+\r\n+- ❌ **关注元素**：看到光/音/风/粒子等元素，直接使用\r\n+- ✅ **关注根源**：理解这些元素为什么有效（文化根源、历史演进、功能需求），然后基于自己的世界观重新设计\r\n+\r\n+### 核心设计原则\r\n+\r\n+1. **根源融合**：深入理解环境元素的本质（为什么需要光？为什么需要音？），然后创造性地融合到世界观中\r\n+2. **自洽体系**：形成独特的、自洽的、演进后的环境叙事体系（而非直接照搬其他游戏）\r\n+3. **玩法一致性**：从世界观设定 → 环境设计 → 玩法机制，形成完整的逻辑链条\r\n+\r\n+### 典型案例\r\n+\r\n+**❌ 错误做法**：\r\n+- 看到《黑暗之魂》的篝火系统 → 直接照搬篝火设计\r\n+- 看到《饥荒》的水表达 → 直接照搬水效果\r\n+- 看到《恶意不息》的动态元素 → 直接堆粒子/风/后处理\r\n+\r\n+**✅ 正确做法**：\r\n+- 理解篝火的**根源**（安全锚点、恢复机制、引导功能）→ 基于自己的世界观设计（神龛/阵法/营地）\r\n+- 理解水的**根源**（玩法机制、物理交互、元素联动）→ 基于自己的玩法设计（够用即可的表达）\r\n+- 理解动态元素的**根源**（氛围、引导、反馈）→ 基于自己的成本/需求选择（先做高性价比的）\r\n+\r\n+### 判断标准\r\n+\r\n+> 问自己：**这个环境元素是否源于世界观设定？还是直接照搬其他游戏？如果只是“好看”，先不做。**\r\n+\r\n+---\r\n+\r\n ## 环境叙事-落地\r\n \r\n > 每做一个新场景，至少交付下面 5 条；做不到就先别加“精细材质”。\r\n \r\n"
                },
                {
                    "date": 1766138844187,
                    "content": "Index: \n===================================================================\n--- \n+++ \n@@ -92,9 +92,8 @@\n - **音效一层**：底噪（风/虫/水/城镇）+ 一条机制反馈（脚步/草/水/火）。\r\n - **光照一层**：主光 + 明暗对比（至少能引导一处重点）。\r\n - **后处理一层**：统一色调（冷/暖/压暗/对比度）让风格收敛。\r\n \r\n-\r\n ---\r\n \r\n ## 环境叙事-交互反馈\r\n \r\n"
                },
                {
                    "date": 1766138940284,
                    "content": "Index: \n===================================================================\n--- \n+++ \n@@ -84,9 +84,9 @@\n ---\r\n \r\n ## 环境叙事-落地\r\n \r\n-> 每做一个新场景，至少交付下面 5 条；做不到就先别加“精细材质”。\r\n+> 每做一个新场景，至少交付下面 5 \r\n \r\n - **静态基底**：形体清晰、可读（不追求精细）。\r\n - **动态一层**：树/草/旗/水面任一“活的动效”。\r\n - **音效一层**：底噪（风/虫/水/城镇）+ 一条机制反馈（脚步/草/水/火）。\r\n"
                },
                {
                    "date": 1766138950467,
                    "content": "Index: \n===================================================================\n--- \n+++ \n@@ -84,9 +84,9 @@\n ---\r\n \r\n ## 环境叙事-落地\r\n \r\n-> 每做一个新场景，至少交付下面 5 \r\n+> 每做一个新场景，遵守下面 5 条\r\n \r\n - **静态基底**：形体清晰、可读（不追求精细）。\r\n - **动态一层**：树/草/旗/水面任一“活的动效”。\r\n - **音效一层**：底噪（风/虫/水/城镇）+ 一条机制反馈（脚步/草/水/火）。\r\n"
                },
                {
                    "date": 1766139312290,
                    "content": "Index: \n===================================================================\n--- \n+++ \n@@ -94,8 +94,82 @@\n - **后处理一层**：统一色调（冷/暖/压暗/对比度）让风格收敛。\r\n \r\n ---\r\n \r\n+## 环境叙事-建筑与地图\r\n+\r\n+> **核心思维**：建筑和地图是环境叙事的“骨架”——用建筑风格和地图布局完成引导、反馈、氛围，并遵循历史演进逻辑形成自洽体系。\r\n+\r\n+### 建筑风格的环境叙事功能\r\n+\r\n+#### 引导功能（最重要）\r\n+\r\n+- **形体可读性**：建筑轮廓清晰、剪影可辨（战斗/夜景尤其重要）\r\n+- **位置引导**：重要建筑（安全点/目标点/危险点）通过位置/高度/明暗对比突出\r\n+- **路径暗示**：建筑布局自然形成“通道/出口/开阔区”的引导（少用箭头）\r\n+\r\n+#### 反馈功能\r\n+\r\n+- **状态变化**：建筑损坏/修复/变化反映玩家行为或剧情进展\r\n+- **动态响应**：建筑灯光/烟雾/声音随玩家行为变化（让世界“活”）\r\n+\r\n+#### 氛围功能\r\n+\r\n+- **风格定调**：建筑风格决定场景情绪（传统/工业/神秘/危险）\r\n+- **留白与层次**：建筑密度/留白/遮挡形成空间节奏（前景遮挡 + 中景主体 + 远景雾化）\r\n+\r\n+### 地图布局的环境叙事功能\r\n+\r\n+#### 引导功能（无UI导航）\r\n+\r\n+- **视觉引导**：地图布局自然形成“主路径/分支/隐藏区域”（通过建筑位置/高度/明暗）\r\n+- **功能分区**：不同区域（安全/危险/探索/战斗）通过建筑风格/布局区分\r\n+- **节奏控制**：开阔区/狭窄区/高低差形成探索节奏（避免单调）\r\n+\r\n+#### 反馈功能\r\n+\r\n+- **动态变化**：地图布局随剧情/玩家行为变化（建筑倒塌/新通道开放/区域封锁）\r\n+- **状态提示**：地图状态反映世界状态（繁荣/衰败/危险/安全）\r\n+\r\n+#### 氛围功能\r\n+\r\n+- **空间情绪**：地图布局决定空间情绪（开阔=自由/压抑，密集=紧张/神秘）\r\n+- **叙事证据**：地图布局本身是叙事（为什么这样布局？反映了什么历史/文化？）\r\n+\r\n+### 历史演进逻辑（遵循“根源融合”）\r\n+\r\n+> **核心问题**：采用\"旧建筑 + 新产物\"的表面拼接，而非遵循历史演进逻辑形成新风格建筑。\r\n+\r\n+#### 错误做法\r\n+\r\n+- ❌ **直接拼接**：传统建筑 + 维多利亚式机械装置（如大水塔、飞艇）\r\n+- ❌ **中西混搭**：直接拼接两种不同文化根源的设计\r\n+- ❌ **未演进**：在原有基础上改造，而非重新设计\r\n+\r\n+#### 正确做法\r\n+\r\n+- ✅ **根源融合**：理解建筑风格的文化根源（为什么是这样？），然后基于自己的世界观重新设计\r\n+- ✅ **自然演进**：保留核心美学（空间布局、比例关系）→ 适应新功能需求 → 使用新材料技术（基于自己的材料体系）→ 形成自洽的、演进后的新风格\r\n+- ✅ **自洽体系**：形成独特的、自洽的、演进后的建筑风格（而非直接照搬其他游戏/文化）\r\n+\r\n+#### 典型案例\r\n+\r\n+**❌ 错误做法**：\r\n+- 看到《赛博朋克2077》的工业建筑 → 直接照搬工业风格\r\n+- 看到《只狼》的日式建筑 → 直接照搬日式风格\r\n+- 看到《逆神者》的维多利亚蒸汽朋克 → 直接照搬维多利亚风格\r\n+\r\n+**✅ 正确做法**：\r\n+- 理解工业建筑的**根源**（功能需求、材料体系、历史演进）→ 基于自己的世界观设计（如果明朝发生工业革命，建筑会如何演进？）\r\n+- 理解日式建筑的**根源**（空间布局、比例关系、文化根源）→ 基于自己的文化体系重新设计\r\n+- 理解维多利亚蒸汽朋克的**根源**（材料体系、结构逻辑、装饰风格）→ 基于中国传统材料体系（木/竹/陶瓷）重新设计\r\n+\r\n+### 判断标准\r\n+\r\n+> 问自己：**这个建筑/地图布局是否源于世界观设定？是否遵循历史演进逻辑？还是直接照搬其他游戏/文化？如果只是“好看”，先不做。**\r\n+\r\n+---\r\n+\r\n ## 环境叙事-交互反馈\r\n \r\n ###  <font color=\"#4a7372\"> \"水\"  </font>\r\n \r\n"
                },
                {
                    "date": 1766139343328,
                    "content": "Index: \n===================================================================\n--- \n+++ \n@@ -100,38 +100,38 @@\n > **核心思维**：建筑和地图是环境叙事的“骨架”——用建筑风格和地图布局完成引导、反馈、氛围，并遵循历史演进逻辑形成自洽体系。\r\n \r\n ### 建筑风格的环境叙事功能\r\n \r\n-#### 引导功能（最重要）\r\n+#### 建筑-引导功能（最重要）\r\n \r\n - **形体可读性**：建筑轮廓清晰、剪影可辨（战斗/夜景尤其重要）\r\n - **位置引导**：重要建筑（安全点/目标点/危险点）通过位置/高度/明暗对比突出\r\n - **路径暗示**：建筑布局自然形成“通道/出口/开阔区”的引导（少用箭头）\r\n \r\n-#### 反馈功能\r\n+#### 建筑-反馈功能\r\n \r\n - **状态变化**：建筑损坏/修复/变化反映玩家行为或剧情进展\r\n - **动态响应**：建筑灯光/烟雾/声音随玩家行为变化（让世界“活”）\r\n \r\n-#### 氛围功能\r\n+#### 建筑-氛围功能\r\n \r\n - **风格定调**：建筑风格决定场景情绪（传统/工业/神秘/危险）\r\n - **留白与层次**：建筑密度/留白/遮挡形成空间节奏（前景遮挡 + 中景主体 + 远景雾化）\r\n \r\n ### 地图布局的环境叙事功能\r\n \r\n-#### 引导功能（无UI导航）\r\n+#### 地图-引导功能（无UI导航）\r\n \r\n - **视觉引导**：地图布局自然形成“主路径/分支/隐藏区域”（通过建筑位置/高度/明暗）\r\n - **功能分区**：不同区域（安全/危险/探索/战斗）通过建筑风格/布局区分\r\n - **节奏控制**：开阔区/狭窄区/高低差形成探索节奏（避免单调）\r\n \r\n-#### 反馈功能\r\n+#### 地图-反馈功能\r\n \r\n - **动态变化**：地图布局随剧情/玩家行为变化（建筑倒塌/新通道开放/区域封锁）\r\n - **状态提示**：地图状态反映世界状态（繁荣/衰败/危险/安全）\r\n \r\n-#### 氛围功能\r\n+#### 地图-氛围功能\r\n \r\n - **空间情绪**：地图布局决定空间情绪（开阔=自由/压抑，密集=紧张/神秘）\r\n - **叙事证据**：地图布局本身是叙事（为什么这样布局？反映了什么历史/文化？）\r\n \r\n"
                },
                {
                    "date": 1766141682645,
                    "content": "Index: \n===================================================================\n--- \n+++ \n@@ -162,8 +162,25 @@\n - 理解工业建筑的**根源**（功能需求、材料体系、历史演进）→ 基于自己的世界观设计（如果明朝发生工业革命，建筑会如何演进？）\r\n - 理解日式建筑的**根源**（空间布局、比例关系、文化根源）→ 基于自己的文化体系重新设计\r\n - 理解维多利亚蒸汽朋克的**根源**（材料体系、结构逻辑、装饰风格）→ 基于中国传统材料体系（木/竹/陶瓷）重新设计\r\n \r\n+#### 基于现实世界地图设计（推荐）\r\n+\r\n+> **核心观点**：基于现实世界地图设计比较合适，因为现实世界的地图布局已经经过历史演进，是自洽的。\r\n+\r\n+**为什么现实世界地图更好**：\r\n+- **历史演进**：现实世界的村落/城市布局是自然演进的结果（适应地形/功能/文化），而非人为设计\r\n+- **自洽体系**：现实世界的布局逻辑是完整的（为什么这样布局？反映了什么需求？），而非表面拼接\r\n+- **引导/反馈/氛围**：现实世界的布局往往天然支持环境叙事（路径引导、功能分区、空间情绪）\r\n+\r\n+**参考方式**：\r\n+- ✅ **参考现实布局逻辑**：理解现实世界村落/城市的布局原因（地形适应、功能需求、文化根源）→ 基于自己的世界观重新设计\r\n+- ✅ **参考现实建筑演进**：理解现实世界建筑如何演进（传统村落 → 现代城市）→ 基于自己的世界观设计演进路径\r\n+- ❌ **直接照搬现实**：不要直接复制现实世界的布局，而要理解其根源后重新设计\r\n+\r\n+**典型案例**：\r\n+- 传统村落布局（如航拍图）：建筑依地形而建、水路贯穿、路径自然形成、重要建筑位置突出 → 理解其布局逻辑（地形适应、功能分区、引导路径）→ 基于自己的世界观重新设计\r\n+\r\n ### 判断标准\r\n \r\n > 问自己：**这个建筑/地图布局是否源于世界观设定？是否遵循历史演进逻辑？还是直接照搬其他游戏/文化？如果只是“好看”，先不做。**\r\n \r\n"
                },
                {
                    "date": 1766144249226,
                    "content": "Index: \n===================================================================\n--- \n+++ \n@@ -174,9 +174,8 @@\n \r\n **参考方式**：\r\n - ✅ **参考现实布局逻辑**：理解现实世界村落/城市的布局原因（地形适应、功能需求、文化根源）→ 基于自己的世界观重新设计\r\n - ✅ **参考现实建筑演进**：理解现实世界建筑如何演进（传统村落 → 现代城市）→ 基于自己的世界观设计演进路径\r\n-- ❌ **直接照搬现实**：不要直接复制现实世界的布局，而要理解其根源后重新设计\r\n \r\n **典型案例**：\r\n - 传统村落布局（如航拍图）：建筑依地形而建、水路贯穿、路径自然形成、重要建筑位置突出 → 理解其布局逻辑（地形适应、功能分区、引导路径）→ 基于自己的世界观重新设计\r\n \r\n"
                },
                {
                    "date": 1766144255165,
                    "content": "Index: \n===================================================================\n--- \n+++ \n@@ -170,13 +170,8 @@\n **为什么现实世界地图更好**：\r\n - **历史演进**：现实世界的村落/城市布局是自然演进的结果（适应地形/功能/文化），而非人为设计\r\n - **自洽体系**：现实世界的布局逻辑是完整的（为什么这样布局？反映了什么需求？），而非表面拼接\r\n - **引导/反馈/氛围**：现实世界的布局往往天然支持环境叙事（路径引导、功能分区、空间情绪）\r\n-\r\n-**参考方式**：\r\n-- ✅ **参考现实布局逻辑**：理解现实世界村落/城市的布局原因（地形适应、功能需求、文化根源）→ 基于自己的世界观重新设计\r\n-- ✅ **参考现实建筑演进**：理解现实世界建筑如何演进（传统村落 → 现代城市）→ 基于自己的世界观设计演进路径\r\n-\r\n **典型案例**：\r\n - 传统村落布局（如航拍图）：建筑依地形而建、水路贯穿、路径自然形成、重要建筑位置突出 → 理解其布局逻辑（地形适应、功能分区、引导路径）→ 基于自己的世界观重新设计\r\n \r\n ### 判断标准\r\n"
                },
                {
                    "date": 1766144271039,
                    "content": "Index: \n===================================================================\n--- \n+++ \n@@ -170,15 +170,13 @@\n **为什么现实世界地图更好**：\r\n - **历史演进**：现实世界的村落/城市布局是自然演进的结果（适应地形/功能/文化），而非人为设计\r\n - **自洽体系**：现实世界的布局逻辑是完整的（为什么这样布局？反映了什么需求？），而非表面拼接\r\n - **引导/反馈/氛围**：现实世界的布局往往天然支持环境叙事（路径引导、功能分区、空间情绪）\r\n+\r\n **典型案例**：\r\n - 传统村落布局（如航拍图）：建筑依地形而建、水路贯穿、路径自然形成、重要建筑位置突出 → 理解其布局逻辑（地形适应、功能分区、引导路径）→ 基于自己的世界观重新设计\r\n \r\n-### 判断标准\r\n \r\n-> 问自己：**这个建筑/地图布局是否源于世界观设定？是否遵循历史演进逻辑？还是直接照搬其他游戏/文化？如果只是“好看”，先不做。**\r\n-\r\n ---\r\n \r\n ## 环境叙事-交互反馈\r\n \r\n"
                },
                {
                    "date": 1766144276763,
                    "content": "Index: \n===================================================================\n--- \n+++ \n@@ -152,12 +152,8 @@\n - ✅ **自洽体系**：形成独特的、自洽的、演进后的建筑风格（而非直接照搬其他游戏/文化）\r\n \r\n #### 典型案例\r\n \r\n-**❌ 错误做法**：\r\n-- 看到《赛博朋克2077》的工业建筑 → 直接照搬工业风格\r\n-- 看到《只狼》的日式建筑 → 直接照搬日式风格\r\n-- 看到《逆神者》的维多利亚蒸汽朋克 → 直接照搬维多利亚风格\r\n \r\n **✅ 正确做法**：\r\n - 理解工业建筑的**根源**（功能需求、材料体系、历史演进）→ 基于自己的世界观设计（如果明朝发生工业革命，建筑会如何演进？）\r\n - 理解日式建筑的**根源**（空间布局、比例关系、文化根源）→ 基于自己的文化体系重新设计\r\n"
                },
                {
                    "date": 1766144292064,
                    "content": "Index: \n===================================================================\n--- \n+++ \n@@ -135,26 +135,14 @@\n - **空间情绪**：地图布局决定空间情绪（开阔=自由/压抑，密集=紧张/神秘）\r\n - **叙事证据**：地图布局本身是叙事（为什么这样布局？反映了什么历史/文化？）\r\n \r\n ### 历史演进逻辑（遵循“根源融合”）\r\n-\r\n-> **核心问题**：采用\"旧建筑 + 新产物\"的表面拼接，而非遵循历史演进逻辑形成新风格建筑。\r\n-\r\n-#### 错误做法\r\n-\r\n-- ❌ **直接拼接**：传统建筑 + 维多利亚式机械装置（如大水塔、飞艇）\r\n-- ❌ **中西混搭**：直接拼接两种不同文化根源的设计\r\n-- ❌ **未演进**：在原有基础上改造，而非重新设计\r\n-\r\n-#### 正确做法\r\n-\r\n - ✅ **根源融合**：理解建筑风格的文化根源（为什么是这样？），然后基于自己的世界观重新设计\r\n - ✅ **自然演进**：保留核心美学（空间布局、比例关系）→ 适应新功能需求 → 使用新材料技术（基于自己的材料体系）→ 形成自洽的、演进后的新风格\r\n - ✅ **自洽体系**：形成独特的、自洽的、演进后的建筑风格（而非直接照搬其他游戏/文化）\r\n \r\n #### 典型案例\r\n \r\n-\r\n **✅ 正确做法**：\r\n - 理解工业建筑的**根源**（功能需求、材料体系、历史演进）→ 基于自己的世界观设计（如果明朝发生工业革命，建筑会如何演进？）\r\n - 理解日式建筑的**根源**（空间布局、比例关系、文化根源）→ 基于自己的文化体系重新设计\r\n - 理解维多利亚蒸汽朋克的**根源**（材料体系、结构逻辑、装饰风格）→ 基于中国传统材料体系（木/竹/陶瓷）重新设计\r\n"
                }
            ],
            "date": 1766136630438,
            "name": "Commit-0",
            "content": "# 环境表现设计理念分析（可一眼扫懂版）\r\n\r\n## 一句话结论\r\n\r\n**环境表现不是“堆美术”，而是用一套可复用的元素（光 / 动效 / 烟雾粒子 / 音 / 场景结构）去完成：引导、反馈、氛围，并尽量与玩法规则绑定。**\r\n\r\n---\r\n\r\n## 核心原理（最重要的 3 件事）\r\n\r\n- **引导**：玩家不用 UI 也知道“往哪走、哪里重要、哪里危险”。（明暗对比 / 色温 / 方向性音效 / 动态吸引点）\r\n- **反馈**：玩家的行为会被环境回应，让世界“活”。（脚步/草动/水波/火光变化/粒子散射）\r\n- **氛围**：玩家能感受到“这里是什么地方、此刻是什么情绪”。（冷暖、留白、空气感、音景层次）\r\n\r\n> 判断标准：**不看 UI、不读字，玩家能否靠环境完成“导航 + 理解 + 感受”。**\r\n\r\n---\r\n\r\n## 环境叙事：公式 + 落地\r\n\r\n### 氛围公式（胡金铨）\r\n\r\n#### 环境的氛围 = 光 + 烟雾 + 景 + 运镜 + 人 + 音\r\n\r\n- **光**：明暗 / 色温 / 聚焦 / 位置 / 光斑 / 光晕 / 光影 → 定调 + 引导 + 规则提示\r\n  - **安全/存档/恢复（示例）**：暖光/稳定光源/聚光范围 = “安全锚点”（篝火、灯笼、神龛、阵法、营地）\r\n  - **危险/禁入（示例）**：偏红/闪烁/逆光剪影/强对比 = “风险提示”（敌巢、陷阱区、Boss场）\r\n  - **探索引导（示例）**：远处一束光/窗缝漏光/光斑落点 = “目标方向”（少用箭头）\r\n- **烟雾**：雾 / 尘 / 雨雪 / 飘絮粒子/ 虫群/ 鸟群 / 云雾 / 烟雾 / 雾霾 → 空气感 + 深度层次\r\n- **景**：形体 / 留白 / 层次 / 遮挡 / 景深 / 远景雾化 / 景深 / 远景雾化 → 可读性 + 叙事证据\r\n- **运镜**：镜头节奏 / 构图变化 / 镜头移动 / 镜头切换 / 镜头抖动 / 镜头旋转 / 镜头拉近 / 镜头拉远 → 信息投放顺序（游戏里对应：视角/镜头/玩家路径节奏）\r\n- **人**：动作 / 停顿 / 剪影 / 表情 / 姿态 / 动作 / 停顿 / 剪影 / 表情 / 姿态 → 情绪锚点（游戏里对应：玩家行为反馈/敌我态势）\r\n- **音**：底噪 + 事件 + 反馈 / 音效 / 音效设计 / 音效 / 音效设计 → 氛围 + 提示 + 叙事补全\r\n\r\n### 从胡金铨画面迁移到游戏的 5 个高性价比细节\r\n\r\n1. **明暗大块面优先**：2–3 个明暗层次先定情绪与空间，细节可以少。\r\n2. **留白就是内容**：雾/天空/空地/远山的“空”＝寂静、距离、未知。\r\n3. **剪影可读性**：先看“形”，再看“细”；战斗和夜景尤其重要。\r\n4. **光束 + 烟雾**：空气结构可见化，同时天然形成引导线（无 UI 导航）。\r\n5. **遮挡 + 远景雾化**：前景遮挡 + 中景主体 + 远景降饱和/雾化 = 低成本纵深。\r\n\r\n---\r\n\r\n![环境表现设计理念分析](环境/Attached_image.png)\r\n![环境表现设计理念分析](环境/Attached_image1.png)\r\n![环境表现设计理念分析](环境/Attached_image2.png)\r\n![环境表现设计理念分析](环境/Attached_image3.png)\r\n![环境表现设计理念分析](环境/Attached_image4.png)\r\n\r\n## 场景制作：最小交付（MVP）清单\r\n\r\n> 每做一个新场景，至少交付下面 5 条；做不到就先别加“精细材质”。\r\n\r\n- **静态基底**：形体清晰、可读（不追求精细）。\r\n- **动态一层**：树/草/旗/水面任一“活的动效”。\r\n- **音效一层**：底噪（风/虫/水/城镇）+ 一条机制反馈（脚步/草/水/火）。\r\n- **光照一层**：主光 + 明暗对比（至少能引导一处重点）。\r\n- **后处理一层**：统一色调（冷/暖/压暗/对比度）让风格收敛。\r\n\r\n### 反面指标（出现就砍）\r\n\r\n- 堆材质细节，但**玩家看不出路径/交互点/危险**。\r\n- 堆粒子/后处理，但**玩法没有任何变化或反馈**。\r\n- 音效很多，但**没有提示/反馈/引导**作用。\r\n\r\n---\r\n\r\n## 资源分配建议（避免做偏）\r\n\r\n> 你当前的判断：**“动态效果/音/光/后处理”往往比“模型细节”更能提升氛围与可读性**。\r\n\r\n- **核心玩法系统**：60–70%\r\n- **风格统一（环境表现系统化）**：20–30%\r\n- **基础视觉效果（够用即可）**：5–10%\r\n- **写实堆料**：0%（除非团队能完整撑住写实链路）\r\n\r\n---\r\n\r\n## 模块化模板（可复用，不写论文）\r\n\r\n> **使用方式**：把下面内容当“交互词典”。只列**可读信号 + 规则/交互效果 + 反馈**，不写实现细节（字段/触发/技术方案）。\r\n\r\n### A. 水：注重水的物理，而不是水的表现，保证玩家能读懂水的状态，水物理是拓展玩法基础\r\n\r\n\r\n**核心思维**：水的价值来自“玩法机制”，视觉只要“能读懂”。\r\n\r\n- **区域**：浅水/深水/危险/安全（颜色/纹理即可区分）\r\n- **状态**：平静/波浪/结冰/污染/魔法（用动效或贴图变化表达）\r\n- **交互反馈（尽量全面）**：\r\n  - **移动**：减速/阻尼/额外行动点消耗/滑行（冰）/打滑（泥）/无法通行（深水）\r\n  - **战斗/元素联动**：导电（雷范围/伤害变化）/冻结（冰封地形）/蒸汽（火+水：遮挡视野/灼伤）/污染（持续DOT/减益）/净化（解除负面）\r\n  - **物理/环境**：浮力（漂浮物/尸体）/冲刷（河流推力）/沉没（重量阈值）/落水（摔落/眩晕）/溺水（窒息计时）\r\n  - **探索/交互**：涉水声暴露/潜行加成（浅水草丛）/可采集（水草/鱼/药）/隐藏通道（浅滩/暗流）/机关（水位/闸门）\r\n  - **表现层**：踩水声/波纹/水花/泡沫/水迹（湿身、脚印）、水面反光（够用即可）\r\n  - **生存/代价（可选）**：体温流失（寒水）/疲劳消耗（逆流）/疾病或感染（污水）/装备受潮（易燃/失灵）/视野折射（误判距离）\r\n- **机制绑定（示例）**：\r\n  - 移动：行动点消耗、路径限制\r\n  - 战斗：水 + 雷/冰/火（范围/状态/遮挡）\r\n  - 探索：隐藏/资源/机关\r\n\r\n![环境表现设计理念分析](环境/水.png)\r\n\r\n### B. 环境音效：底噪 + 事件 + 反馈（够用即可）\r\n\r\n**核心思维**：音效要支持玩法（提示/反馈/引导），其次才是“好听”。\r\n\r\n- **底噪（氛围）**：风/虫/水/城镇人声（让场景“活”）\r\n- **事件提示（引导）**：远处怪、机关、目标区域（方向性/距离衰减）\r\n- **交互反馈（规则，尽量全面）**：\r\n  - **脚步材质**：木/石/泥/草/雪/金属/沙（可读“地形”）\r\n  - **水相关**：踩水/涉水/落水/游泳（可读“水位与风险”）\r\n  - **植被/布料**：草动/树叶摩擦/旗帜拍打（可读“风与动向”）\r\n  - **火与能量**：火焰噼啪/熄灭/爆燃、法术嗡鸣（可读“状态变化”）\r\n  - **交互与UI替代**：开门/拾取/机关启动/宝箱（确认反馈）\r\n  - **危险提示**：远处吼叫/脚步逼近/低频轰鸣（提前预警与引导）\r\n  - **状态提示**：湿/冻/燃/毒/流血/诅咒（用“音色差异”让玩家听出状态）\r\n  - **地形危险**：塌陷/碎石滚落/冰裂/泥陷（用预警音提示“将要发生”）\r\n\r\n### C. 光源：三作用 + 分类（保留你的分类体系）\r\n\r\n**核心思维**：光源的三个作用——**玩法机制、氛围营造、地图引导**。\r\n\r\n#### 光源的地图引导（最重要）\r\n\r\n- **明暗**：亮=重要/安全，暗=隐藏/危险（按你游戏规则定义）\r\n- **颜色**：暖=安全/人类活动；冷=神秘/异界；红=危险/战斗\r\n- **动态**：闪烁/移动/渐变＝吸引注意力、指示方向\r\n\r\n#### 光源的“规则提示”（不涉及实现）\r\n\r\n- **安全/可停留**：暖色/稳定/柔和衰减（营地、神龛、旅店、路灯聚光）\r\n- **存档/重生/恢复**：更强的“仪式感光”（符文、光晕、聚光、点亮音）让玩家无需UI也能理解\r\n- **危险/警戒**：红光/逆光剪影/闪烁/强对比（敌巢、Boss、陷阱区）\r\n- **禁入/损伤**：黑光/低饱和/异常闪烁（诅咒区、污染区、精神压迫区）\r\n\r\n#### 光源系统的分类\r\n\r\n1. **自然光源（环境光源）**\r\n   - 白天：太阳光、天空光、云层遮挡、轻反射\r\n   - 黑夜：月光、星光、弱环境光\r\n2. **人工光源（交互光源）**\r\n   - 火把（玩家）、灯笼/火堆（场景）、魔法光（技能）\r\n3. **玩法光源（机制光源）**\r\n   - 视野/隐藏/战斗/探索（与规则绑定，优先级最高）\r\n\r\n#### 技术实现（够用即可）\r\n\r\n- **基础**：Directional Light + 阴影 + 简单后处理调色\r\n- **可选增强**：动态时间、引导光源标记、少量光晕/粒子\r\n\r\n![环境表现设计理念分析](环境/attached_image6.png)\r\n![环境表现设计理念分析](环境/attached_image7.png)\r\n![环境表现设计理念分析](环境/attached_image8.png)\r\n---\r\n\r\n## 你当前这套方法论的优势（给未来的自己）\r\n\r\n- **可拓展**：同一套“光/音/动效/雾/留白/剪影”能无限复用，风格越做越统一。\r\n- **可控成本**：不依赖高精度模型，也能做出“有气”的场景。\r\n- **可服务玩法**：环境表现直接成为玩法的一部分（引导/反馈/规则）。\r\n"
        }
    ]
}